[
  {
    "listeners": 626,
    "recorded_at": "2025-11-10T20:02:11.260357+01:00",
    "raw_valid": true,
    "song_session_id": "1289333a-0ae1-4672-a0d1-f9e77afcdfe0"
  },
  {
    "listeners": 617,
    "recorded_at": "2025-11-10T20:02:41.290803+01:00",
    "raw_valid": true,
    "song_session_id": "1289333a-0ae1-4672-a0d1-f9e77afcdfe0"
  },
  {
    "listeners": 621,
    "recorded_at": "2025-11-10T20:03:11.317654+01:00",
    "raw_valid": true,
    "song_session_id": "1289333a-0ae1-4672-a0d1-f9e77afcdfe0"
  },
  {
    "listeners": 622,
    "recorded_at": "2025-11-10T20:03:41.348039+01:00",
    "raw_valid": true,
    "song_session_id": "1289333a-0ae1-4672-a0d1-f9e77afcdfe0"
  },
  {
    "listeners": 610,
    "recorded_at": "2025-11-10T20:04:51.442858+01:00",
    "raw_valid": true,
    "song_session_id": "4f280edd-b52f-4d34-973b-ce512e2636ef"
  },
  {
    "listeners": 618,
    "recorded_at": "2025-11-10T20:05:21.445064+01:00",
    "raw_valid": true,
    "song_session_id": "4f280edd-b52f-4d34-973b-ce512e2636ef"
  },
  {
    "listeners": 621,
    "recorded_at": "2025-11-10T20:05:51.453704+01:00",
    "raw_valid": true,
    "song_session_id": "4f280edd-b52f-4d34-973b-ce512e2636ef"
  },
  {
    "listeners": 618,
    "recorded_at": "2025-11-10T20:06:21.454165+01:00",
    "raw_valid": true,
    "song_session_id": "b7ee185d-063d-4c4f-98fd-c74d52f6aecd"
  },
  {
    "listeners": 623,
    "recorded_at": "2025-11-10T20:06:51.465169+01:00",
    "raw_valid": true,
    "song_session_id": "b7ee185d-063d-4c4f-98fd-c74d52f6aecd"
  },
  {
    "listeners": 614,
    "recorded_at": "2025-11-10T20:07:21.469715+01:00",
    "raw_valid": true,
    "song_session_id": "b7ee185d-063d-4c4f-98fd-c74d52f6aecd"
  },
  {
    "listeners": 620,
    "recorded_at": "2025-11-10T20:07:51.479917+01:00",
    "raw_valid": true,
    "song_session_id": "b7ee185d-063d-4c4f-98fd-c74d52f6aecd"
  },
  {
    "listeners": 615,
    "recorded_at": "2025-11-10T20:08:21.490526+01:00",
    "raw_valid": true,
    "song_session_id": "b7ee185d-063d-4c4f-98fd-c74d52f6aecd"
  },
  {
    "listeners": 615,
    "recorded_at": "2025-11-10T20:08:51.501746+01:00",
    "raw_valid": true,
    "song_session_id": "b7ee185d-063d-4c4f-98fd-c74d52f6aecd"
  },
  {
    "listeners": 630,
    "recorded_at": "2025-11-10T20:09:21.512218+01:00",
    "raw_valid": true,
    "song_session_id": "edec0803-c9b6-49e6-992a-5b486775c2e9"
  },
  {
    "listeners": 622,
    "recorded_at": "2025-11-10T20:09:51.522783+01:00",
    "raw_valid": true,
    "song_session_id": "edec0803-c9b6-49e6-992a-5b486775c2e9"
  },
  {
    "listeners": 622,
    "recorded_at": "2025-11-10T20:10:21.553413+01:00",
    "raw_valid": true,
    "song_session_id": "edec0803-c9b6-49e6-992a-5b486775c2e9"
  },
  {
    "listeners": 629,
    "recorded_at": "2025-11-10T20:10:51.581697+01:00",
    "raw_valid": true,
    "song_session_id": "edec0803-c9b6-49e6-992a-5b486775c2e9"
  },
  {
    "listeners": 613,
    "recorded_at": "2025-11-10T20:11:21.612062+01:00",
    "raw_valid": true,
    "song_session_id": "edec0803-c9b6-49e6-992a-5b486775c2e9"
  },
  {
    "listeners": 628,
    "recorded_at": "2025-11-10T20:11:51.642447+01:00",
    "raw_valid": true,
    "song_session_id": "edec0803-c9b6-49e6-992a-5b486775c2e9"
  },
  {
    "listeners": 614,
    "recorded_at": "2025-11-10T20:12:21.672943+01:00",
    "raw_valid": true,
    "song_session_id": "f9746e7d-4ac0-433b-bd55-d122d7e59bd9"
  },
  {
    "listeners": 623,
    "recorded_at": "2025-11-10T20:12:51.703388+01:00",
    "raw_valid": true,
    "song_session_id": "f9746e7d-4ac0-433b-bd55-d122d7e59bd9"
  },
  {
    "listeners": 610,
    "recorded_at": "2025-11-10T20:13:21.733846+01:00",
    "raw_valid": true,
    "song_session_id": "f9746e7d-4ac0-433b-bd55-d122d7e59bd9"
  },
  {
    "listeners": 611,
    "recorded_at": "2025-11-10T20:13:51.764211+01:00",
    "raw_valid": true,
    "song_session_id": "f9746e7d-4ac0-433b-bd55-d122d7e59bd9"
  },
  {
    "listeners": 627,
    "recorded_at": "2025-11-10T20:14:21.794643+01:00",
    "raw_valid": true,
    "song_session_id": "f9746e7d-4ac0-433b-bd55-d122d7e59bd9"
  },
  {
    "listeners": 615,
    "recorded_at": "2025-11-10T20:14:51.805699+01:00",
    "raw_valid": true,
    "song_session_id": "f9746e7d-4ac0-433b-bd55-d122d7e59bd9"
  },
  {
    "listeners": 622,
    "recorded_at": "2025-11-10T20:15:21.813674+01:00",
    "raw_valid": true,
    "song_session_id": "c0e51554-9e50-4116-9f51-a8209d85ac55"
  },
  {
    "listeners": 623,
    "recorded_at": "2025-11-10T20:15:51.844132+01:00",
    "raw_valid": true,
    "song_session_id": "c0e51554-9e50-4116-9f51-a8209d85ac55"
  },
  {
    "listeners": 620,
    "recorded_at": "2025-11-10T20:16:21.852512+01:00",
    "raw_valid": true,
    "song_session_id": "c0e51554-9e50-4116-9f51-a8209d85ac55"
  },
  {
    "listeners": 627,
    "recorded_at": "2025-11-10T20:16:51.882952+01:00",
    "raw_valid": true,
    "song_session_id": "c0e51554-9e50-4116-9f51-a8209d85ac55"
  },
  {
    "listeners": 624,
    "recorded_at": "2025-11-10T20:17:21.913376+01:00",
    "raw_valid": true,
    "song_session_id": "c0e51554-9e50-4116-9f51-a8209d85ac55"
  },
  {
    "listeners": 610,
    "recorded_at": "2025-11-10T20:18:32.002482+01:00",
    "raw_valid": true,
    "song_session_id": "c0e51554-9e50-4116-9f51-a8209d85ac55"
  },
  {
    "listeners": 613,
    "recorded_at": "2025-11-10T20:19:02.015236+01:00",
    "raw_valid": true,
    "song_session_id": "c0e51554-9e50-4116-9f51-a8209d85ac55"
  },
  {
    "listeners": 623,
    "recorded_at": "2025-11-10T20:19:32.026248+01:00",
    "raw_valid": true,
    "song_session_id": "16606fc2-5ca8-4d33-b549-82629bdb8353"
  },
  {
    "listeners": 624,
    "recorded_at": "2025-11-10T20:20:02.034301+01:00",
    "raw_valid": true,
    "song_session_id": "16606fc2-5ca8-4d33-b549-82629bdb8353"
  },
  {
    "listeners": 618,
    "recorded_at": "2025-11-10T20:20:32.044767+01:00",
    "raw_valid": true,
    "song_session_id": "16606fc2-5ca8-4d33-b549-82629bdb8353"
  },
  {
    "listeners": 629,
    "recorded_at": "2025-11-10T20:21:02.056761+01:00",
    "raw_valid": true,
    "song_session_id": "16606fc2-5ca8-4d33-b549-82629bdb8353"
  },
  {
    "listeners": 614,
    "recorded_at": "2025-11-10T20:21:32.064704+01:00",
    "raw_valid": true,
    "song_session_id": "16606fc2-5ca8-4d33-b549-82629bdb8353"
  },
  {
    "listeners": 611,
    "recorded_at": "2025-11-10T20:22:02.075723+01:00",
    "raw_valid": true,
    "song_session_id": "16606fc2-5ca8-4d33-b549-82629bdb8353"
  },
  {
    "listeners": 615,
    "recorded_at": "2025-11-10T20:22:32.086415+01:00",
    "raw_valid": true,
    "song_session_id": "16606fc2-5ca8-4d33-b549-82629bdb8353"
  },
  {
    "listeners": 627,
    "recorded_at": "2025-11-10T20:23:02.093818+01:00",
    "raw_valid": true,
    "song_session_id": "16606fc2-5ca8-4d33-b549-82629bdb8353"
  },
  {
    "listeners": 629,
    "recorded_at": "2025-11-10T20:23:32.104571+01:00",
    "raw_valid": true,
    "song_session_id": "4ceeb414-9658-46e7-b677-2b4d9d7ab379"
  },
  {
    "listeners": 627,
    "recorded_at": "2025-11-10T20:24:02.135207+01:00",
    "raw_valid": true,
    "song_session_id": "4ceeb414-9658-46e7-b677-2b4d9d7ab379"
  },
  {
    "listeners": 628,
    "recorded_at": "2025-11-10T20:24:32.165602+01:00",
    "raw_valid": true,
    "song_session_id": "4ceeb414-9658-46e7-b677-2b4d9d7ab379"
  },
  {
    "listeners": 618,
    "recorded_at": "2025-11-10T20:25:02.196037+01:00",
    "raw_valid": true,
    "song_session_id": "4ceeb414-9658-46e7-b677-2b4d9d7ab379"
  },
  {
    "listeners": 613,
    "recorded_at": "2025-11-10T20:25:32.221705+01:00",
    "raw_valid": true,
    "song_session_id": "4ceeb414-9658-46e7-b677-2b4d9d7ab379"
  },
  {
    "listeners": 618,
    "recorded_at": "2025-11-10T20:26:02.229738+01:00",
    "raw_valid": true,
    "song_session_id": "4ceeb414-9658-46e7-b677-2b4d9d7ab379"
  },
  {
    "listeners": 618,
    "recorded_at": "2025-11-10T20:26:32.253701+01:00",
    "raw_valid": true,
    "song_session_id": "4ceeb414-9658-46e7-b677-2b4d9d7ab379"
  },
  {
    "listeners": 630,
    "recorded_at": "2025-11-10T20:27:02.269729+01:00",
    "raw_valid": true,
    "song_session_id": "4ceeb414-9658-46e7-b677-2b4d9d7ab379"
  },
  {
    "listeners": 627,
    "recorded_at": "2025-11-10T20:27:32.300152+01:00",
    "raw_valid": true,
    "song_session_id": "4ceeb414-9658-46e7-b677-2b4d9d7ab379"
  },
  {
    "listeners": 627,
    "recorded_at": "2025-11-10T20:28:02.317709+01:00",
    "raw_valid": true,
    "song_session_id": "4ceeb414-9658-46e7-b677-2b4d9d7ab379"
  },
  {
    "listeners": 621,
    "recorded_at": "2025-11-10T20:28:32.348116+01:00",
    "raw_valid": true,
    "song_session_id": "5683dd14-8f6f-4ba7-a180-741a0ca81c57"
  },
  {
    "listeners": 630,
    "recorded_at": "2025-11-10T20:29:02.365756+01:00",
    "raw_valid": true,
    "song_session_id": "5683dd14-8f6f-4ba7-a180-741a0ca81c57"
  },
  {
    "listeners": 619,
    "recorded_at": "2025-11-10T20:29:32.396191+01:00",
    "raw_valid": true,
    "song_session_id": "5683dd14-8f6f-4ba7-a180-741a0ca81c57"
  },
  {
    "listeners": 610,
    "recorded_at": "2025-11-10T20:30:02.397054+01:00",
    "raw_valid": true,
    "song_session_id": "5683dd14-8f6f-4ba7-a180-741a0ca81c57"
  },
  {
    "listeners": 630,
    "recorded_at": "2025-11-10T20:30:32.427502+01:00",
    "raw_valid": true,
    "song_session_id": "5683dd14-8f6f-4ba7-a180-741a0ca81c57"
  },
  {
    "listeners": 623,
    "recorded_at": "2025-11-10T20:31:02.457901+01:00",
    "raw_valid": true,
    "song_session_id": "5683dd14-8f6f-4ba7-a180-741a0ca81c57"
  },
  {
    "listeners": 625,
    "recorded_at": "2025-11-10T20:32:12.541579+01:00",
    "raw_valid": true,
    "song_session_id": "4b1874c9-2717-43c3-978f-48e6ba377b7f"
  },
  {
    "listeners": 628,
    "recorded_at": "2025-11-10T20:32:42.553258+01:00",
    "raw_valid": true,
    "song_session_id": "4b1874c9-2717-43c3-978f-48e6ba377b7f"
  },
  {
    "listeners": 625,
    "recorded_at": "2025-11-10T20:33:12.563893+01:00",
    "raw_valid": true,
    "song_session_id": "4b1874c9-2717-43c3-978f-48e6ba377b7f"
  },
  {
    "listeners": 612,
    "recorded_at": "2025-11-10T20:33:42.575095+01:00",
    "raw_valid": true,
    "song_session_id": "4b1874c9-2717-43c3-978f-48e6ba377b7f"
  },
  {
    "listeners": 628,
    "recorded_at": "2025-11-10T20:34:12.586381+01:00",
    "raw_valid": true,
    "song_session_id": "4b1874c9-2717-43c3-978f-48e6ba377b7f"
  },
  {
    "listeners": 618,
    "recorded_at": "2025-11-10T20:34:42.597410+01:00",
    "raw_valid": true,
    "song_session_id": "33c44a4b-e99c-434f-bf05-a6749a7d571f"
  },
  {
    "listeners": 625,
    "recorded_at": "2025-11-10T20:35:12.609299+01:00",
    "raw_valid": true,
    "song_session_id": "33c44a4b-e99c-434f-bf05-a6749a7d571f"
  },
  {
    "listeners": 626,
    "recorded_at": "2025-11-10T20:35:42.619692+01:00",
    "raw_valid": true,
    "song_session_id": "33c44a4b-e99c-434f-bf05-a6749a7d571f"
  },
  {
    "listeners": 626,
    "recorded_at": "2025-11-10T20:36:12.629740+01:00",
    "raw_valid": true,
    "song_session_id": "33c44a4b-e99c-434f-bf05-a6749a7d571f"
  },
  {
    "listeners": 622,
    "recorded_at": "2025-11-10T20:36:42.637674+01:00",
    "raw_valid": true,
    "song_session_id": "33c44a4b-e99c-434f-bf05-a6749a7d571f"
  },
  {
    "listeners": 624,
    "recorded_at": "2025-11-10T20:37:12.648835+01:00",
    "raw_valid": true,
    "song_session_id": "33c44a4b-e99c-434f-bf05-a6749a7d571f"
  },
  {
    "listeners": 625,
    "recorded_at": "2025-11-10T20:37:42.679614+01:00",
    "raw_valid": true,
    "song_session_id": "1eff2c4b-b23c-4af9-badd-5372afea7ba6"
  },
  {
    "listeners": 630,
    "recorded_at": "2025-11-10T20:38:12.693667+01:00",
    "raw_valid": true,
    "song_session_id": "1eff2c4b-b23c-4af9-badd-5372afea7ba6"
  },
  {
    "listeners": 616,
    "recorded_at": "2025-11-10T20:38:42.724071+01:00",
    "raw_valid": true,
    "song_session_id": "1eff2c4b-b23c-4af9-badd-5372afea7ba6"
  },
  {
    "listeners": 623,
    "recorded_at": "2025-11-10T20:39:12.754544+01:00",
    "raw_valid": true,
    "song_session_id": "1eff2c4b-b23c-4af9-badd-5372afea7ba6"
  },
  {
    "listeners": 617,
    "recorded_at": "2025-11-10T20:39:42.757710+01:00",
    "raw_valid": true,
    "song_session_id": "1eff2c4b-b23c-4af9-badd-5372afea7ba6"
  },
  {
    "listeners": 629,
    "recorded_at": "2025-11-10T20:40:12.765551+01:00",
    "raw_valid": true,
    "song_session_id": "1eff2c4b-b23c-4af9-badd-5372afea7ba6"
  },
  {
    "listeners": 626,
    "recorded_at": "2025-11-10T20:40:42.796003+01:00",
    "raw_valid": true,
    "song_session_id": "d456fe04-f0c2-47d9-ae70-96b0b0bc9086"
  },
  {
    "listeners": 610,
    "recorded_at": "2025-11-10T20:41:12.813703+01:00",
    "raw_valid": true,
    "song_session_id": "d456fe04-f0c2-47d9-ae70-96b0b0bc9086"
  },
  {
    "listeners": 615,
    "recorded_at": "2025-11-10T20:41:42.843688+01:00",
    "raw_valid": true,
    "song_session_id": "d456fe04-f0c2-47d9-ae70-96b0b0bc9086"
  },
  {
    "listeners": 622,
    "recorded_at": "2025-11-10T20:42:12.874101+01:00",
    "raw_valid": true,
    "song_session_id": "d456fe04-f0c2-47d9-ae70-96b0b0bc9086"
  },
  {
    "listeners": 626,
    "recorded_at": "2025-11-10T20:42:42.904552+01:00",
    "raw_valid": true,
    "song_session_id": "d456fe04-f0c2-47d9-ae70-96b0b0bc9086"
  },
  {
    "listeners": 623,
    "recorded_at": "2025-11-10T20:43:12.917674+01:00",
    "raw_valid": true,
    "song_session_id": "d456fe04-f0c2-47d9-ae70-96b0b0bc9086"
  },
  {
    "listeners": 615,
    "recorded_at": "2025-11-10T20:43:42.948064+01:00",
    "raw_valid": true,
    "song_session_id": "d456fe04-f0c2-47d9-ae70-96b0b0bc9086"
  },
  {
    "listeners": 627,
    "recorded_at": "2025-11-10T20:44:12.978509+01:00",
    "raw_valid": true,
    "song_session_id": "d456fe04-f0c2-47d9-ae70-96b0b0bc9086"
  },
  {
    "listeners": 621,
    "recorded_at": "2025-11-10T20:44:43.009116+01:00",
    "raw_valid": true,
    "song_session_id": "ab65220c-abe5-4c67-aa8b-99033e57c3bf"
  },
  {
    "listeners": 624,
    "recorded_at": "2025-11-10T20:45:53.105175+01:00",
    "raw_valid": true,
    "song_session_id": "ab65220c-abe5-4c67-aa8b-99033e57c3bf"
  },
  {
    "listeners": 624,
    "recorded_at": "2025-11-10T20:46:23.115526+01:00",
    "raw_valid": true,
    "song_session_id": "40a6b749-9352-4f38-b4c3-0a58a7944288"
  },
  {
    "listeners": 617,
    "recorded_at": "2025-11-10T20:46:53.126141+01:00",
    "raw_valid": true,
    "song_session_id": "40a6b749-9352-4f38-b4c3-0a58a7944288"
  },
  {
    "listeners": 619,
    "recorded_at": "2025-11-10T20:47:23.137152+01:00",
    "raw_valid": true,
    "song_session_id": "40a6b749-9352-4f38-b4c3-0a58a7944288"
  },
  {
    "listeners": 630,
    "recorded_at": "2025-11-10T20:47:53.141712+01:00",
    "raw_valid": true,
    "song_session_id": "40a6b749-9352-4f38-b4c3-0a58a7944288"
  },
  {
    "listeners": 611,
    "recorded_at": "2025-11-10T20:48:23.151948+01:00",
    "raw_valid": true,
    "song_session_id": "40a6b749-9352-4f38-b4c3-0a58a7944288"
  },
  {
    "listeners": 619,
    "recorded_at": "2025-11-10T20:48:53.162059+01:00",
    "raw_valid": true,
    "song_session_id": "40a6b749-9352-4f38-b4c3-0a58a7944288"
  },
  {
    "listeners": 627,
    "recorded_at": "2025-11-10T20:49:23.172630+01:00",
    "raw_valid": true,
    "song_session_id": "40a6b749-9352-4f38-b4c3-0a58a7944288"
  },
  {
    "listeners": 613,
    "recorded_at": "2025-11-10T20:49:53.182563+01:00",
    "raw_valid": true,
    "song_session_id": "40a6b749-9352-4f38-b4c3-0a58a7944288"
  },
  {
    "listeners": 629,
    "recorded_at": "2025-11-10T20:50:23.190599+01:00",
    "raw_valid": true,
    "song_session_id": "8ac08567-f687-41fa-88d4-c0fb5d7c7acb"
  },
  {
    "listeners": 623,
    "recorded_at": "2025-11-10T20:50:53.202709+01:00",
    "raw_valid": true,
    "song_session_id": "8ac08567-f687-41fa-88d4-c0fb5d7c7acb"
  },
  {
    "listeners": 618,
    "recorded_at": "2025-11-10T20:51:23.213202+01:00",
    "raw_valid": true,
    "song_session_id": "8ac08567-f687-41fa-88d4-c0fb5d7c7acb"
  },
  {
    "listeners": 628,
    "recorded_at": "2025-11-10T20:51:53.243618+01:00",
    "raw_valid": true,
    "song_session_id": "8ac08567-f687-41fa-88d4-c0fb5d7c7acb"
  },
  {
    "listeners": 612,
    "recorded_at": "2025-11-10T20:52:23.274025+01:00",
    "raw_valid": true,
    "song_session_id": "8ac08567-f687-41fa-88d4-c0fb5d7c7acb"
  },
  {
    "listeners": 619,
    "recorded_at": "2025-11-10T20:52:53.301666+01:00",
    "raw_valid": true,
    "song_session_id": "8ac08567-f687-41fa-88d4-c0fb5d7c7acb"
  },
  {
    "listeners": 626,
    "recorded_at": "2025-11-10T20:53:23.317679+01:00",
    "raw_valid": true,
    "song_session_id": "8ac08567-f687-41fa-88d4-c0fb5d7c7acb"
  },
  {
    "listeners": 625,
    "recorded_at": "2025-11-10T20:53:53.348059+01:00",
    "raw_valid": true,
    "song_session_id": "8ac08567-f687-41fa-88d4-c0fb5d7c7acb"
  },
  {
    "listeners": 626,
    "recorded_at": "2025-11-10T20:54:23.373284+01:00",
    "raw_valid": true,
    "song_session_id": "93256b6e-dc1a-4868-978e-a8fb38e1e6bd"
  },
  {
    "listeners": 618,
    "recorded_at": "2025-11-10T20:54:53.403752+01:00",
    "raw_valid": true,
    "song_session_id": "93256b6e-dc1a-4868-978e-a8fb38e1e6bd"
  },
  {
    "listeners": 622,
    "recorded_at": "2025-11-10T20:55:23.434183+01:00",
    "raw_valid": true,
    "song_session_id": "93256b6e-dc1a-4868-978e-a8fb38e1e6bd"
  },
  {
    "listeners": 611,
    "recorded_at": "2025-11-10T20:55:53.453729+01:00",
    "raw_valid": true,
    "song_session_id": "93256b6e-dc1a-4868-978e-a8fb38e1e6bd"
  },
  {
    "listeners": 613,
    "recorded_at": "2025-11-10T20:56:23.484152+01:00",
    "raw_valid": true,
    "song_session_id": "93256b6e-dc1a-4868-978e-a8fb38e1e6bd"
  },
  {
    "listeners": 613,
    "recorded_at": "2025-11-10T20:56:53.485304+01:00",
    "raw_valid": true,
    "song_session_id": "93256b6e-dc1a-4868-978e-a8fb38e1e6bd"
  },
  {
    "listeners": 630,
    "recorded_at": "2025-11-10T20:57:23.515825+01:00",
    "raw_valid": true,
    "song_session_id": "93256b6e-dc1a-4868-978e-a8fb38e1e6bd"
  },
  {
    "listeners": 622,
    "recorded_at": "2025-11-10T20:57:53.518013+01:00",
    "raw_valid": true,
    "song_session_id": "93256b6e-dc1a-4868-978e-a8fb38e1e6bd"
  },
  {
    "listeners": 611,
    "recorded_at": "2025-11-10T20:58:23.548442+01:00",
    "raw_valid": true,
    "song_session_id": "c32469dc-4c29-49d3-b1cd-33f3f237d43c"
  },
  {
    "listeners": 617,
    "recorded_at": "2025-11-10T20:59:33.646514+01:00",
    "raw_valid": true,
    "song_session_id": "c32469dc-4c29-49d3-b1cd-33f3f237d43c"
  },
  {
    "listeners": 615,
    "recorded_at": "2025-11-10T21:00:03.658303+01:00",
    "raw_valid": true,
    "song_session_id": "c32469dc-4c29-49d3-b1cd-33f3f237d43c"
  },
  {
    "listeners": 629,
    "recorded_at": "2025-11-10T21:00:33.661694+01:00",
    "raw_valid": true,
    "song_session_id": "6861b334-3274-4839-ab37-2871d6c425a6"
  },
  {
    "listeners": 522,
    "recorded_at": "2025-11-10T21:01:03.672799+01:00",
    "raw_valid": true,
    "song_session_id": "6861b334-3274-4839-ab37-2871d6c425a6"
  },
  {
    "listeners": 514,
    "recorded_at": "2025-11-10T21:01:33.683705+01:00",
    "raw_valid": true,
    "song_session_id": "6861b334-3274-4839-ab37-2871d6c425a6"
  },
  {
    "listeners": 520,
    "recorded_at": "2025-11-10T21:02:03.694595+01:00",
    "raw_valid": true,
    "song_session_id": "6861b334-3274-4839-ab37-2871d6c425a6"
  },
  {
    "listeners": 516,
    "recorded_at": "2025-11-10T21:02:33.705006+01:00",
    "raw_valid": true,
    "song_session_id": "6861b334-3274-4839-ab37-2871d6c425a6"
  },
  {
    "listeners": 527,
    "recorded_at": "2025-11-10T21:03:03.715250+01:00",
    "raw_valid": true,
    "song_session_id": "6861b334-3274-4839-ab37-2871d6c425a6"
  },
  {
    "listeners": 516,
    "recorded_at": "2025-11-10T21:03:33.724607+01:00",
    "raw_valid": true,
    "song_session_id": "6861b334-3274-4839-ab37-2871d6c425a6"
  },
  {
    "listeners": 527,
    "recorded_at": "2025-11-10T21:04:03.735165+01:00",
    "raw_valid": true,
    "song_session_id": "6861b334-3274-4839-ab37-2871d6c425a6"
  },
  {
    "listeners": 519,
    "recorded_at": "2025-11-10T21:04:33.746741+01:00",
    "raw_valid": true,
    "song_session_id": "bf9a04bd-352a-4098-b9ce-1b5c91e71d32"
  },
  {
    "listeners": 519,
    "recorded_at": "2025-11-10T21:05:03.773713+01:00",
    "raw_valid": true,
    "song_session_id": "bf9a04bd-352a-4098-b9ce-1b5c91e71d32"
  },
  {
    "listeners": 510,
    "recorded_at": "2025-11-10T21:05:33.804194+01:00",
    "raw_valid": true,
    "song_session_id": "bf9a04bd-352a-4098-b9ce-1b5c91e71d32"
  },
  {
    "listeners": 527,
    "recorded_at": "2025-11-10T21:06:03.813711+01:00",
    "raw_valid": true,
    "song_session_id": "bf9a04bd-352a-4098-b9ce-1b5c91e71d32"
  },
  {
    "listeners": 518,
    "recorded_at": "2025-11-10T21:06:33.837728+01:00",
    "raw_valid": true,
    "song_session_id": "bf9a04bd-352a-4098-b9ce-1b5c91e71d32"
  },
  {
    "listeners": 513,
    "recorded_at": "2025-11-10T21:07:03.868170+01:00",
    "raw_valid": true,
    "song_session_id": "bf9a04bd-352a-4098-b9ce-1b5c91e71d32"
  },
  {
    "listeners": 525,
    "recorded_at": "2025-11-10T21:07:33.898581+01:00",
    "raw_valid": true,
    "song_session_id": "bf9a04bd-352a-4098-b9ce-1b5c91e71d32"
  },
  {
    "listeners": 510,
    "recorded_at": "2025-11-10T21:08:03.901696+01:00",
    "raw_valid": true,
    "song_session_id": "bf9a04bd-352a-4098-b9ce-1b5c91e71d32"
  },
  {
    "listeners": 526,
    "recorded_at": "2025-11-10T21:08:33.932134+01:00",
    "raw_valid": true,
    "song_session_id": "8dc26b68-4a53-4e16-98fd-fb1420a71703"
  },
  {
    "listeners": 513,
    "recorded_at": "2025-11-10T21:09:03.933737+01:00",
    "raw_valid": true,
    "song_session_id": "8dc26b68-4a53-4e16-98fd-fb1420a71703"
  },
  {
    "listeners": 520,
    "recorded_at": "2025-11-10T21:09:33.964154+01:00",
    "raw_valid": true,
    "song_session_id": "8dc26b68-4a53-4e16-98fd-fb1420a71703"
  },
  {
    "listeners": 524,
    "recorded_at": "2025-11-10T21:10:03.994629+01:00",
    "raw_valid": true,
    "song_session_id": "8dc26b68-4a53-4e16-98fd-fb1420a71703"
  },
  {
    "listeners": 510,
    "recorded_at": "2025-11-10T21:10:34.025076+01:00",
    "raw_valid": true,
    "song_session_id": "8dc26b68-4a53-4e16-98fd-fb1420a71703"
  },
  {
    "listeners": 516,
    "recorded_at": "2025-11-10T21:11:04.036317+01:00",
    "raw_valid": true,
    "song_session_id": "8dc26b68-4a53-4e16-98fd-fb1420a71703"
  },
  {
    "listeners": 511,
    "recorded_at": "2025-11-10T21:11:34.058626+01:00",
    "raw_valid": true,
    "song_session_id": "8dc26b68-4a53-4e16-98fd-fb1420a71703"
  },
  {
    "listeners": 529,
    "recorded_at": "2025-11-10T21:12:04.089107+01:00",
    "raw_valid": true,
    "song_session_id": "8dc26b68-4a53-4e16-98fd-fb1420a71703"
  },
  {
    "listeners": 514,
    "recorded_at": "2025-11-10T21:13:14.158245+01:00",
    "raw_valid": true,
    "song_session_id": "62fafd61-c05e-4958-809b-83040e0d0d50"
  },
  {
    "listeners": 524,
    "recorded_at": "2025-11-10T21:13:44.166258+01:00",
    "raw_valid": true,
    "song_session_id": "62fafd61-c05e-4958-809b-83040e0d0d50"
  },
  {
    "listeners": 513,
    "recorded_at": "2025-11-10T21:14:14.176998+01:00",
    "raw_valid": true,
    "song_session_id": "62fafd61-c05e-4958-809b-83040e0d0d50"
  },
  {
    "listeners": 525,
    "recorded_at": "2025-11-10T21:14:44.188140+01:00",
    "raw_valid": true,
    "song_session_id": "62fafd61-c05e-4958-809b-83040e0d0d50"
  },
  {
    "listeners": 515,
    "recorded_at": "2025-11-10T21:15:14.199107+01:00",
    "raw_valid": true,
    "song_session_id": "62fafd61-c05e-4958-809b-83040e0d0d50"
  },
  {
    "listeners": 528,
    "recorded_at": "2025-11-10T21:15:44.210011+01:00",
    "raw_valid": true,
    "song_session_id": "98be4c41-e3e1-4313-8a43-e598b541689c"
  },
  {
    "listeners": 528,
    "recorded_at": "2025-11-10T21:16:14.220414+01:00",
    "raw_valid": true,
    "song_session_id": "98be4c41-e3e1-4313-8a43-e598b541689c"
  },
  {
    "listeners": 513,
    "recorded_at": "2025-11-10T21:16:44.221695+01:00",
    "raw_valid": true,
    "song_session_id": "98be4c41-e3e1-4313-8a43-e598b541689c"
  },
  {
    "listeners": 515,
    "recorded_at": "2025-11-10T21:17:14.232311+01:00",
    "raw_valid": true,
    "song_session_id": "98be4c41-e3e1-4313-8a43-e598b541689c"
  },
  {
    "listeners": 525,
    "recorded_at": "2025-11-10T21:17:44.243066+01:00",
    "raw_valid": true,
    "song_session_id": "98be4c41-e3e1-4313-8a43-e598b541689c"
  },
  {
    "listeners": 512,
    "recorded_at": "2025-11-10T21:18:14.254770+01:00",
    "raw_valid": true,
    "song_session_id": "98be4c41-e3e1-4313-8a43-e598b541689c"
  },
  {
    "listeners": 525,
    "recorded_at": "2025-11-10T21:18:44.286836+01:00",
    "raw_valid": true,
    "song_session_id": "5adea715-068b-4d76-a6f8-7e579cd21c39"
  },
  {
    "listeners": 518,
    "recorded_at": "2025-11-10T21:19:14.309716+01:00",
    "raw_valid": true,
    "song_session_id": "5adea715-068b-4d76-a6f8-7e579cd21c39"
  },
  {
    "listeners": 522,
    "recorded_at": "2025-11-10T21:19:44.317704+01:00",
    "raw_valid": true,
    "song_session_id": "5adea715-068b-4d76-a6f8-7e579cd21c39"
  },
  {
    "listeners": 530,
    "recorded_at": "2025-11-10T21:20:14.333656+01:00",
    "raw_valid": true,
    "song_session_id": "5adea715-068b-4d76-a6f8-7e579cd21c39"
  },
  {
    "listeners": 513,
    "recorded_at": "2025-11-10T21:20:44.349707+01:00",
    "raw_valid": true,
    "song_session_id": "5adea715-068b-4d76-a6f8-7e579cd21c39"
  },
  {
    "listeners": 514,
    "recorded_at": "2025-11-10T21:21:14.365691+01:00",
    "raw_valid": true,
    "song_session_id": "5adea715-068b-4d76-a6f8-7e579cd21c39"
  },
  {
    "listeners": 517,
    "recorded_at": "2025-11-10T21:21:44.396152+01:00",
    "raw_valid": true,
    "song_session_id": "5adea715-068b-4d76-a6f8-7e579cd21c39"
  },
  {
    "listeners": 512,
    "recorded_at": "2025-11-10T21:22:14.397088+01:00",
    "raw_valid": true,
    "song_session_id": "5adea715-068b-4d76-a6f8-7e579cd21c39"
  },
  {
    "listeners": 530,
    "recorded_at": "2025-11-10T21:22:44.427529+01:00",
    "raw_valid": true,
    "song_session_id": "2594d90f-d60d-48d4-89b6-6884efe0e55f"
  },
  {
    "listeners": 519,
    "recorded_at": "2025-11-10T21:23:14.457983+01:00",
    "raw_valid": true,
    "song_session_id": "2594d90f-d60d-48d4-89b6-6884efe0e55f"
  },
  {
    "listeners": 524,
    "recorded_at": "2025-11-10T21:23:44.461741+01:00",
    "raw_valid": true,
    "song_session_id": "2594d90f-d60d-48d4-89b6-6884efe0e55f"
  },
  {
    "listeners": 522,
    "recorded_at": "2025-11-10T21:24:14.492220+01:00",
    "raw_valid": true,
    "song_session_id": "2594d90f-d60d-48d4-89b6-6884efe0e55f"
  },
  {
    "listeners": 528,
    "recorded_at": "2025-11-10T21:24:44.509735+01:00",
    "raw_valid": true,
    "song_session_id": "2594d90f-d60d-48d4-89b6-6884efe0e55f"
  },
  {
    "listeners": 528,
    "recorded_at": "2025-11-10T21:25:14.540182+01:00",
    "raw_valid": true,
    "song_session_id": "2594d90f-d60d-48d4-89b6-6884efe0e55f"
  },
  {
    "listeners": 528,
    "recorded_at": "2025-11-10T21:25:44.570627+01:00",
    "raw_valid": true,
    "song_session_id": "2594d90f-d60d-48d4-89b6-6884efe0e55f"
  },
  {
    "listeners": 517,
    "recorded_at": "2025-11-10T21:26:54.651129+01:00",
    "raw_valid": true,
    "song_session_id": "a5dabf52-1f08-4522-9db6-371e83d2a0ab"
  },
  {
    "listeners": 524,
    "recorded_at": "2025-11-10T21:27:24.662400+01:00",
    "raw_valid": true,
    "song_session_id": "a5dabf52-1f08-4522-9db6-371e83d2a0ab"
  },
  {
    "listeners": 529,
    "recorded_at": "2025-11-10T21:27:54.674259+01:00",
    "raw_valid": true,
    "song_session_id": "a5dabf52-1f08-4522-9db6-371e83d2a0ab"
  },
  {
    "listeners": 518,
    "recorded_at": "2025-11-10T21:28:24.680615+01:00",
    "raw_valid": true,
    "song_session_id": "a5dabf52-1f08-4522-9db6-371e83d2a0ab"
  },
  {
    "listeners": 518,
    "recorded_at": "2025-11-10T21:28:54.690782+01:00",
    "raw_valid": true,
    "song_session_id": "a5dabf52-1f08-4522-9db6-371e83d2a0ab"
  },
  {
    "listeners": 525,
    "recorded_at": "2025-11-10T21:29:24.701549+01:00",
    "raw_valid": true,
    "song_session_id": "a5dabf52-1f08-4522-9db6-371e83d2a0ab"
  },
  {
    "listeners": 514,
    "recorded_at": "2025-11-10T21:29:54.711726+01:00",
    "raw_valid": true,
    "song_session_id": "a5dabf52-1f08-4522-9db6-371e83d2a0ab"
  },
  {
    "listeners": 516,
    "recorded_at": "2025-11-10T21:30:24.722297+01:00",
    "raw_valid": true,
    "song_session_id": "ddcad300-b796-4416-ac2d-32acdf38fa2e"
  },
  {
    "listeners": 518,
    "recorded_at": "2025-11-10T21:30:54.732617+01:00",
    "raw_valid": true,
    "song_session_id": "ddcad300-b796-4416-ac2d-32acdf38fa2e"
  },
  {
    "listeners": 514,
    "recorded_at": "2025-11-10T21:31:24.741316+01:00",
    "raw_valid": true,
    "song_session_id": "ddcad300-b796-4416-ac2d-32acdf38fa2e"
  },
  {
    "listeners": 525,
    "recorded_at": "2025-11-10T21:31:54.752677+01:00",
    "raw_valid": true,
    "song_session_id": "ddcad300-b796-4416-ac2d-32acdf38fa2e"
  },
  {
    "listeners": 522,
    "recorded_at": "2025-11-10T21:32:24.783743+01:00",
    "raw_valid": true,
    "song_session_id": "ddcad300-b796-4416-ac2d-32acdf38fa2e"
  },
  {
    "listeners": 519,
    "recorded_at": "2025-11-10T21:32:54.789726+01:00",
    "raw_valid": true,
    "song_session_id": "ddcad300-b796-4416-ac2d-32acdf38fa2e"
  },
  {
    "listeners": 519,
    "recorded_at": "2025-11-10T21:33:24.813698+01:00",
    "raw_valid": true,
    "song_session_id": "917ebf45-8486-45de-b444-be65f25b8e9a"
  },
  {
    "listeners": 527,
    "recorded_at": "2025-11-10T21:33:54.844177+01:00",
    "raw_valid": true,
    "song_session_id": "917ebf45-8486-45de-b444-be65f25b8e9a"
  },
  {
    "listeners": 523,
    "recorded_at": "2025-11-10T21:34:24.845703+01:00",
    "raw_valid": true,
    "song_session_id": "917ebf45-8486-45de-b444-be65f25b8e9a"
  },
  {
    "listeners": 511,
    "recorded_at": "2025-11-10T21:34:54.876167+01:00",
    "raw_valid": true,
    "song_session_id": "917ebf45-8486-45de-b444-be65f25b8e9a"
  },
  {
    "listeners": 510,
    "recorded_at": "2025-11-10T21:35:24.906640+01:00",
    "raw_valid": true,
    "song_session_id": "917ebf45-8486-45de-b444-be65f25b8e9a"
  },
  {
    "listeners": 516,
    "recorded_at": "2025-11-10T21:35:54.937067+01:00",
    "raw_valid": true,
    "song_session_id": "917ebf45-8486-45de-b444-be65f25b8e9a"
  },
  {
    "listeners": 510,
    "recorded_at": "2025-11-10T21:36:24.957674+01:00",
    "raw_valid": true,
    "song_session_id": "552f7f72-0597-4df2-9cbe-2289bc7662b1"
  },
  {
    "listeners": 524,
    "recorded_at": "2025-11-10T21:36:54.988076+01:00",
    "raw_valid": true,
    "song_session_id": "552f7f72-0597-4df2-9cbe-2289bc7662b1"
  },
  {
    "listeners": 519,
    "recorded_at": "2025-11-10T21:37:25.018535+01:00",
    "raw_valid": true,
    "song_session_id": "552f7f72-0597-4df2-9cbe-2289bc7662b1"
  },
  {
    "listeners": 513,
    "recorded_at": "2025-11-10T21:37:55.021683+01:00",
    "raw_valid": true,
    "song_session_id": "552f7f72-0597-4df2-9cbe-2289bc7662b1"
  },
  {
    "listeners": 523,
    "recorded_at": "2025-11-10T21:38:25.052077+01:00",
    "raw_valid": true,
    "song_session_id": "552f7f72-0597-4df2-9cbe-2289bc7662b1"
  },
  {
    "listeners": 517,
    "recorded_at": "2025-11-10T21:38:55.082564+01:00",
    "raw_valid": true,
    "song_session_id": "552f7f72-0597-4df2-9cbe-2289bc7662b1"
  },
  {
    "listeners": 522,
    "recorded_at": "2025-11-10T21:39:25.093693+01:00",
    "raw_valid": true,
    "song_session_id": "bbe9a3b8-14c8-4554-8618-b7b16b257c85"
  },
  {
    "listeners": 520,
    "recorded_at": "2025-11-10T21:40:35.233291+01:00",
    "raw_valid": true,
    "song_session_id": "bbe9a3b8-14c8-4554-8618-b7b16b257c85"
  },
  {
    "listeners": 529,
    "recorded_at": "2025-11-10T21:41:05.234253+01:00",
    "raw_valid": true,
    "song_session_id": "bbe9a3b8-14c8-4554-8618-b7b16b257c85"
  },
  {
    "listeners": 528,
    "recorded_at": "2025-11-10T21:41:35.245503+01:00",
    "raw_valid": true,
    "song_session_id": "bbe9a3b8-14c8-4554-8618-b7b16b257c85"
  },
  {
    "listeners": 518,
    "recorded_at": "2025-11-10T21:42:05.246777+01:00",
    "raw_valid": true,
    "song_session_id": "bbe9a3b8-14c8-4554-8618-b7b16b257c85"
  },
  {
    "listeners": 519,
    "recorded_at": "2025-11-10T21:42:35.257240+01:00",
    "raw_valid": true,
    "song_session_id": "bbe9a3b8-14c8-4554-8618-b7b16b257c85"
  },
  {
    "listeners": 526,
    "recorded_at": "2025-11-10T21:43:05.258686+01:00",
    "raw_valid": true,
    "song_session_id": "bbe9a3b8-14c8-4554-8618-b7b16b257c85"
  },
  {
    "listeners": 525,
    "recorded_at": "2025-11-10T21:43:35.259707+01:00",
    "raw_valid": true,
    "song_session_id": "91584baf-414a-4670-9045-922b452c1a0a"
  },
  {
    "listeners": 518,
    "recorded_at": "2025-11-10T21:44:05.270759+01:00",
    "raw_valid": true,
    "song_session_id": "91584baf-414a-4670-9045-922b452c1a0a"
  },
  {
    "listeners": 517,
    "recorded_at": "2025-11-10T21:44:35.280903+01:00",
    "raw_valid": true,
    "song_session_id": "91584baf-414a-4670-9045-922b452c1a0a"
  },
  {
    "listeners": 520,
    "recorded_at": "2025-11-10T21:45:05.291031+01:00",
    "raw_valid": true,
    "song_session_id": "91584baf-414a-4670-9045-922b452c1a0a"
  },
  {
    "listeners": 512,
    "recorded_at": "2025-11-10T21:45:35.303349+01:00",
    "raw_valid": true,
    "song_session_id": "91584baf-414a-4670-9045-922b452c1a0a"
  },
  {
    "listeners": 511,
    "recorded_at": "2025-11-10T21:46:05.317689+01:00",
    "raw_valid": true,
    "song_session_id": "91584baf-414a-4670-9045-922b452c1a0a"
  },
  {
    "listeners": 528,
    "recorded_at": "2025-11-10T21:46:35.331980+01:00",
    "raw_valid": true,
    "song_session_id": "39f917ca-4bd8-4200-82ee-f539cdcb723f"
  },
  {
    "listeners": 529,
    "recorded_at": "2025-11-10T21:47:05.362412+01:00",
    "raw_valid": true,
    "song_session_id": "39f917ca-4bd8-4200-82ee-f539cdcb723f"
  },
  {
    "listeners": 527,
    "recorded_at": "2025-11-10T21:47:35.392835+01:00",
    "raw_valid": true,
    "song_session_id": "39f917ca-4bd8-4200-82ee-f539cdcb723f"
  },
  {
    "listeners": 530,
    "recorded_at": "2025-11-10T21:48:05.423251+01:00",
    "raw_valid": true,
    "song_session_id": "39f917ca-4bd8-4200-82ee-f539cdcb723f"
  },
  {
    "listeners": 525,
    "recorded_at": "2025-11-10T21:48:35.442936+01:00",
    "raw_valid": true,
    "song_session_id": "39f917ca-4bd8-4200-82ee-f539cdcb723f"
  },
  {
    "listeners": 510,
    "recorded_at": "2025-11-10T21:49:05.469695+01:00",
    "raw_valid": true,
    "song_session_id": "39f917ca-4bd8-4200-82ee-f539cdcb723f"
  },
  {
    "listeners": 518,
    "recorded_at": "2025-11-10T21:49:35.477677+01:00",
    "raw_valid": true,
    "song_session_id": "4b627fc5-6b17-4e77-866b-1a1359a20f74"
  },
  {
    "listeners": 530,
    "recorded_at": "2025-11-10T21:50:05.501711+01:00",
    "raw_valid": true,
    "song_session_id": "4b627fc5-6b17-4e77-866b-1a1359a20f74"
  },
  {
    "listeners": 522,
    "recorded_at": "2025-11-10T21:50:35.517695+01:00",
    "raw_valid": true,
    "song_session_id": "4b627fc5-6b17-4e77-866b-1a1359a20f74"
  },
  {
    "listeners": 521,
    "recorded_at": "2025-11-10T21:51:05.533700+01:00",
    "raw_valid": true,
    "song_session_id": "4b627fc5-6b17-4e77-866b-1a1359a20f74"
  },
  {
    "listeners": 529,
    "recorded_at": "2025-11-10T21:51:35.549715+01:00",
    "raw_valid": true,
    "song_session_id": "4b627fc5-6b17-4e77-866b-1a1359a20f74"
  },
  {
    "listeners": 520,
    "recorded_at": "2025-11-10T21:52:05.557532+01:00",
    "raw_valid": true,
    "song_session_id": "4b627fc5-6b17-4e77-866b-1a1359a20f74"
  },
  {
    "listeners": 526,
    "recorded_at": "2025-11-10T21:52:35.587945+01:00",
    "raw_valid": true,
    "song_session_id": "4b627fc5-6b17-4e77-866b-1a1359a20f74"
  },
  {
    "listeners": 520,
    "recorded_at": "2025-11-10T21:53:05.597687+01:00",
    "raw_valid": true,
    "song_session_id": "4b627fc5-6b17-4e77-866b-1a1359a20f74"
  },
  {
    "listeners": 530,
    "recorded_at": "2025-11-10T21:54:15.678008+01:00",
    "raw_valid": true,
    "song_session_id": "8071a0d7-355e-4735-9adb-68ea318d4264"
  },
  {
    "listeners": 523,
    "recorded_at": "2025-11-10T21:54:45.678730+01:00",
    "raw_valid": true,
    "song_session_id": "8071a0d7-355e-4735-9adb-68ea318d4264"
  },
  {
    "listeners": 515,
    "recorded_at": "2025-11-10T21:55:15.689589+01:00",
    "raw_valid": true,
    "song_session_id": "8071a0d7-355e-4735-9adb-68ea318d4264"
  },
  {
    "listeners": 520,
    "recorded_at": "2025-11-10T21:55:45.701785+01:00",
    "raw_valid": true,
    "song_session_id": "8071a0d7-355e-4735-9adb-68ea318d4264"
  },
  {
    "listeners": 516,
    "recorded_at": "2025-11-10T21:56:15.709840+01:00",
    "raw_valid": true,
    "song_session_id": "8071a0d7-355e-4735-9adb-68ea318d4264"
  },
  {
    "listeners": 517,
    "recorded_at": "2025-11-10T21:56:45.720509+01:00",
    "raw_valid": true,
    "song_session_id": "06d4566b-97dd-4e80-af42-c26580c3a370"
  },
  {
    "listeners": 515,
    "recorded_at": "2025-11-10T21:57:15.730751+01:00",
    "raw_valid": true,
    "song_session_id": "06d4566b-97dd-4e80-af42-c26580c3a370"
  },
  {
    "listeners": 520,
    "recorded_at": "2025-11-10T21:57:45.740835+01:00",
    "raw_valid": true,
    "song_session_id": "06d4566b-97dd-4e80-af42-c26580c3a370"
  },
  {
    "listeners": 518,
    "recorded_at": "2025-11-10T21:58:15.750880+01:00",
    "raw_valid": true,
    "song_session_id": "06d4566b-97dd-4e80-af42-c26580c3a370"
  },
  {
    "listeners": 529,
    "recorded_at": "2025-11-10T21:58:45.762614+01:00",
    "raw_valid": true,
    "song_session_id": "06d4566b-97dd-4e80-af42-c26580c3a370"
  },
  {
    "listeners": 528,
    "recorded_at": "2025-11-10T21:59:15.773712+01:00",
    "raw_valid": true,
    "song_session_id": "06d4566b-97dd-4e80-af42-c26580c3a370"
  },
  {
    "listeners": 525,
    "recorded_at": "2025-11-10T21:59:45.803124+01:00",
    "raw_valid": true,
    "song_session_id": "06d4566b-97dd-4e80-af42-c26580c3a370"
  },
  {
    "listeners": 521,
    "recorded_at": "2025-11-10T22:00:15.813711+01:00",
    "raw_valid": true,
    "song_session_id": "06d4566b-97dd-4e80-af42-c26580c3a370"
  },
  {
    "listeners": 513,
    "recorded_at": "2025-11-10T22:00:45.844129+01:00",
    "raw_valid": true,
    "song_session_id": "d9317340-eeeb-4429-8ac9-0cfd67b58a8d"
  },
  {
    "listeners": 515,
    "recorded_at": "2025-11-10T22:01:15.874561+01:00",
    "raw_valid": true,
    "song_session_id": "d9317340-eeeb-4429-8ac9-0cfd67b58a8d"
  },
  {
    "listeners": 529,
    "recorded_at": "2025-11-10T22:01:45.883147+01:00",
    "raw_valid": true,
    "song_session_id": "d9317340-eeeb-4429-8ac9-0cfd67b58a8d"
  }
]