[
  {
    "last_update": "2025-12-06 01:57:16",
    "song": {
      "musicAuthor": "Hex",
      "musicCover": "https://i.scdn.co/image/ab67616d00004851a224357a82f21d6f9f2e584a",
      "musicTitle": "Nikdy Nebolo Lepšie",
      "radio": "Rádio ROCK",
      "startTime": "02:56"
    },
    "recorded_at": "2025-12-06T02:57:16.846871+01:00",
    "raw_valid": true,
    "song_session_id": "d0529bf4-5c5e-4236-a290-ff9a27239fdd"
  },
  {
    "last_update": "2025-12-06 02:01:16",
    "song": {
      "musicAuthor": "Queen",
      "musicCover": "https://i.scdn.co/image/ab67616d00004851e98d08fbea1a2f03229abc20",
      "musicTitle": "A Kind Of Magic",
      "radio": "Rádio ROCK",
      "startTime": "03:01"
    },
    "recorded_at": "2025-12-06T03:01:17.114270+01:00",
    "raw_valid": true,
    "song_session_id": "06d29134-d007-4769-a54f-80d6e5b755b3"
  },
  {
    "last_update": "2025-12-06 02:06:23",
    "song": {
      "musicAuthor": "Billy Barman",
      "musicCover": "https://i.scdn.co/image/ab67616d00004851d98c7bc0c8671b5727b2a044",
      "musicTitle": "Traja",
      "radio": "Rádio ROCK",
      "startTime": "03:05"
    },
    "recorded_at": "2025-12-06T03:06:23.379994+01:00",
    "raw_valid": true,
    "song_session_id": "169f55d2-748c-423d-b8cd-0ec6f42523f8"
  },
  {
    "last_update": "2025-12-06 02:09:23",
    "song": {
      "musicAuthor": "The Youniverse",
      "musicCover": "https://i.scdn.co/image/ab67616d00004851edec1fd617f7c4481d51588d",
      "musicTitle": "Aftershock",
      "radio": "Rádio ROCK",
      "startTime": "03:08"
    },
    "recorded_at": "2025-12-06T03:09:23.712564+01:00",
    "raw_valid": true,
    "song_session_id": "37842616-40ae-4d94-a942-08c3dd11f85c"
  },
  {
    "last_update": "2025-12-06 02:12:23",
    "song": {
      "musicAuthor": "Pearl Jam",
      "musicCover": "https://i.scdn.co/image/ab67616d00004851d400d27cba05bb0545533864",
      "musicTitle": "Even Flow",
      "radio": "Rádio ROCK",
      "startTime": "03:11"
    },
    "recorded_at": "2025-12-06T03:12:23.910293+01:00",
    "raw_valid": true,
    "song_session_id": "181d022b-2aea-4564-b243-2d8cd676cb77"
  },
  {
    "last_update": "2025-12-06 02:17:25",
    "song": {
      "musicAuthor": "Elán",
      "musicCover": "https://static.radia.sk/covers/32/d11ee088-e1b8-4897-98a6-1191a6da3dc5.jpg",
      "musicTitle": "Čo Je? Čo Je? Čo Chceš?",
      "radio": "Rádio ROCK",
      "startTime": "03:16"
    },
    "recorded_at": "2025-12-06T03:17:25.598893+01:00",
    "raw_valid": true,
    "song_session_id": "f18fa127-a438-4924-b96b-966b1254fd19"
  },
  {
    "last_update": "2025-12-06 02:20:26",
    "song": {
      "musicAuthor": "Slobodná Európa",
      "musicCover": "https://static.radia.sk/covers/32/0df0eaa4-f9e5-40ea-a20b-22dfb901e91a.jpg",
      "musicTitle": "Dry '69",
      "radio": "Rádio ROCK",
      "startTime": "03:20"
    },
    "recorded_at": "2025-12-06T03:20:26.312412+01:00",
    "raw_valid": true,
    "song_session_id": "baf5f4a6-ebce-45a0-bbb7-0da9d7447d8b"
  },
  {
    "last_update": "2025-12-06 02:23:26",
    "song": {
      "musicAuthor": "Crazy Town",
      "musicCover": "https://i.scdn.co/image/ab67616d00004851be3d60f650c3b9dbad061f7f",
      "musicTitle": "Butterfly",
      "radio": "Rádio ROCK",
      "startTime": "03:22"
    },
    "recorded_at": "2025-12-06T03:23:26.560631+01:00",
    "raw_valid": true,
    "song_session_id": "43bdd86d-3a90-472f-b9e8-da03fbfa9714"
  },
  {
    "last_update": "2025-12-06 02:27:31",
    "song": {
      "musicAuthor": "Imt Smile",
      "musicCover": "https://static.radia.sk/covers/32/22a45fbb-1d58-4b53-ae16-2924695866eb.jpg",
      "musicTitle": "Vrany",
      "radio": "Rádio ROCK",
      "startTime": "03:26"
    },
    "recorded_at": "2025-12-06T03:27:32.393169+01:00",
    "raw_valid": true,
    "song_session_id": "f3be38c8-a3ae-43fb-83a9-098143e1768e"
  },
  {
    "last_update": "2025-12-06 02:31:34",
    "song": {
      "musicAuthor": "Tublatanka",
      "musicCover": "https://i.scdn.co/image/ab67616d000048514b813e7e56c0e4c85f8cb5d0",
      "musicTitle": "Láska, Drž Ma Nad Hladinou",
      "radio": "Rádio ROCK",
      "startTime": "03:30"
    },
    "recorded_at": "2025-12-06T03:31:35.487488+01:00",
    "raw_valid": true,
    "song_session_id": "f81ffd87-ab2c-4803-8a11-01214673defd"
  },
  {
    "last_update": "2025-12-06 02:36:35",
    "song": {
      "musicAuthor": "Deep Purple",
      "musicCover": "https://i.scdn.co/image/ab67616d00004851a729c9c3dec04b99d889c66f",
      "musicTitle": "Smoke On The Water",
      "radio": "Rádio ROCK",
      "startTime": "03:35"
    },
    "recorded_at": "2025-12-06T03:36:36.548101+01:00",
    "raw_valid": true,
    "song_session_id": "a21ab419-ba76-46e0-a73a-31a01571687d"
  },
  {
    "last_update": "2025-12-06 02:42:37",
    "song": {
      "musicAuthor": "The Paranoid",
      "musicCover": "https://static.radia.sk/covers/32/6a4240f7-0415-4426-b5d7-761e04b4985b.jpg",
      "musicTitle": "Unos",
      "radio": "Rádio ROCK",
      "startTime": "03:41"
    },
    "recorded_at": "2025-12-06T03:42:37.187965+01:00",
    "raw_valid": true,
    "song_session_id": "849f6f99-d08b-4124-a60e-265279118f7c"
  },
  {
    "last_update": "2025-12-06 02:49:07",
    "song": {
      "musicAuthor": "Metallica",
      "musicCover": "https://i.scdn.co/image/ab67616d00004851cf84c5b276431b473e924802",
      "musicTitle": "The Unforgiven",
      "radio": "Rádio ROCK",
      "startTime": "03:48"
    },
    "recorded_at": "2025-12-06T03:49:07.913410+01:00",
    "raw_valid": true,
    "song_session_id": "69e4e21a-c39e-4293-90ad-d983b0a4cec3"
  },
  {
    "last_update": "2025-12-06 02:55:08",
    "song": {
      "musicAuthor": "Bijouterrier",
      "musicCover": "https://i.scdn.co/image/ab67616d000048517d0015ba5cd2366db03e38f8",
      "musicTitle": "Wheeler Dealer",
      "radio": "Rádio ROCK",
      "startTime": "03:54"
    },
    "recorded_at": "2025-12-06T03:55:09.205165+01:00",
    "raw_valid": true,
    "song_session_id": "a012935c-fefa-4f5d-a907-7a3476b96ff1"
  },
  {
    "last_update": "2025-12-06 02:58:09",
    "song": {
      "musicAuthor": "Gladiátor",
      "musicCover": "https://i.scdn.co/image/ab67616d00004851b5e43a9994d7a9bcf2c73efd",
      "musicTitle": "Divoký Dážď",
      "radio": "Rádio ROCK",
      "startTime": "03:57"
    },
    "recorded_at": "2025-12-06T03:58:09.911961+01:00",
    "raw_valid": true,
    "song_session_id": "cf7d0ae0-8970-4953-921b-55c5650e1569"
  },
  {
    "last_update": "2025-12-06 03:02:10",
    "song": {
      "musicAuthor": "The Police",
      "musicCover": "https://i.scdn.co/image/ab67616d00004851c8e97cafeb2acb85b21a777e",
      "musicTitle": "Every Breath You Take",
      "radio": "Rádio ROCK",
      "startTime": "04:01"
    },
    "recorded_at": "2025-12-06T04:02:10.627095+01:00",
    "raw_valid": true,
    "song_session_id": "aae76eeb-8a95-404b-b7fb-fc939ec4a4ad"
  },
  {
    "last_update": "2025-12-06 03:06:10",
    "song": {
      "musicAuthor": "Iné Kafe",
      "musicCover": "https://i.scdn.co/image/ab67616d000048518fc6f6fb2fa1a8a407bf218a",
      "musicTitle": "Sínus Dopadu",
      "radio": "Rádio ROCK",
      "startTime": "04:05"
    },
    "recorded_at": "2025-12-06T04:06:11.725495+01:00",
    "raw_valid": true,
    "song_session_id": "c799d116-f6f7-4778-ad9c-8490354f1531"
  },
  {
    "last_update": "2025-12-06 03:10:12",
    "song": {
      "musicAuthor": "Elán",
      "musicCover": "https://i.scdn.co/image/ab67616d000048516f93b2fb748d6ada175e7a53",
      "musicTitle": "Kamaráti",
      "radio": "Rádio ROCK",
      "startTime": "04:10"
    },
    "recorded_at": "2025-12-06T04:10:13.218588+01:00",
    "raw_valid": true,
    "song_session_id": "ef8855c3-5c6f-4a44-94b7-f9dc568815ca"
  },
  {
    "last_update": "2025-12-06 03:13:12",
    "song": {
      "musicAuthor": "Imagine Dragons",
      "musicCover": "https://i.scdn.co/image/ab67616d0000485125e1a02097987b3480c7a8c5",
      "musicTitle": "Follow You",
      "radio": "Rádio ROCK",
      "startTime": "04:12"
    },
    "recorded_at": "2025-12-06T04:13:13.386041+01:00",
    "raw_valid": true,
    "song_session_id": "04726b96-800b-49d4-8953-02de51439674"
  },
  {
    "last_update": "2025-12-06 03:16:14",
    "song": {
      "musicAuthor": "Uherčík, Ďurinda, Griglák, Horváth",
      "musicCover": "/layout/covers/default.png",
      "musicTitle": "Loď do neznáma",
      "radio": "Rádio ROCK",
      "startTime": "04:15"
    },
    "recorded_at": "2025-12-06T04:16:14.244597+01:00",
    "raw_valid": true,
    "song_session_id": "123d1bcd-cf56-4474-b507-b12b7f2a83fd"
  },
  {
    "last_update": "2025-12-06 03:20:16",
    "song": {
      "musicAuthor": "Konflikt",
      "musicCover": "https://i.scdn.co/image/ab67616d0000485128f8180f5629cf40c2930876",
      "musicTitle": "To Sme My",
      "radio": "Rádio ROCK",
      "startTime": "04:19"
    },
    "recorded_at": "2025-12-06T04:20:16.541317+01:00",
    "raw_valid": true,
    "song_session_id": "8f9181fa-d394-4ed3-8feb-c4786993df91"
  },
  {
    "last_update": "2025-12-06 03:24:17",
    "song": {
      "musicAuthor": "The Red Hot Chili Peppers",
      "musicCover": "https://i.scdn.co/image/ab67616d00004851153d79816d853f2694b2cc70",
      "musicTitle": "Under The Bridge",
      "radio": "Rádio ROCK",
      "startTime": "04:24"
    },
    "recorded_at": "2025-12-06T04:24:17.351770+01:00",
    "raw_valid": true,
    "song_session_id": "a12c544d-9004-4a41-824b-9255d1e3b617"
  },
  {
    "last_update": "2025-12-06 03:29:19",
    "song": {
      "musicAuthor": "Tublatanka",
      "musicCover": "https://static.radia.sk/covers/32/7ee86987-baad-48a6-9afa-0ca560d378f2.jpg",
      "musicTitle": "Tuláčik S Dobrou Povesťou",
      "radio": "Rádio ROCK",
      "startTime": "04:28"
    },
    "recorded_at": "2025-12-06T04:29:19.829110+01:00",
    "raw_valid": true,
    "song_session_id": "d9cd9473-22c6-4213-936d-8f2e23afff72"
  },
  {
    "last_update": "2025-12-06 03:34:22",
    "song": {
      "musicAuthor": "The Paranoid",
      "musicCover": "https://i.scdn.co/image/ab67616d000048515948d67ae9ad90d4c74e396e",
      "musicTitle": "Skúšam Ťa Nájsť",
      "radio": "Rádio ROCK",
      "startTime": "04:34"
    },
    "recorded_at": "2025-12-06T04:34:22.786961+01:00",
    "raw_valid": true,
    "song_session_id": "268058e3-565c-4d97-b446-82bb2bcee31e"
  },
  {
    "last_update": "2025-12-06 03:38:22",
    "song": {
      "musicAuthor": "Motörhead",
      "musicCover": "https://i.scdn.co/image/ab67616d00004851b00cf2fa71e5c784525ae7c4",
      "musicTitle": "Overkill",
      "radio": "Rádio ROCK",
      "startTime": "04:37"
    },
    "recorded_at": "2025-12-06T04:38:23.383149+01:00",
    "raw_valid": true,
    "song_session_id": "9bd34281-0e44-4714-97b1-01f3479353ff"
  },
  {
    "last_update": "2025-12-06 03:41:23",
    "song": {
      "musicAuthor": "Elán",
      "musicCover": "https://i.scdn.co/image/ab67616d00004851113f109764730da72f73225c",
      "musicTitle": "Čaba Neblázni",
      "radio": "Rádio ROCK",
      "startTime": "04:40"
    },
    "recorded_at": "2025-12-06T04:41:24.752919+01:00",
    "raw_valid": true,
    "song_session_id": "9959c06a-fb9e-4987-b1be-0a5baae72d7c"
  },
  {
    "last_update": "2025-12-06 03:46:25",
    "song": {
      "musicAuthor": "Hex",
      "musicCover": "https://static.radia.sk/covers/32/7e0ab803-009c-4005-b833-612a2ee53cfd.jpg",
      "musicTitle": "Dobrý Motýľ",
      "radio": "Rádio ROCK",
      "startTime": "04:45"
    },
    "recorded_at": "2025-12-06T04:46:25.673033+01:00",
    "raw_valid": true,
    "song_session_id": "8d3a1459-c2a1-4ac8-bef4-844c2a27c202"
  },
  {
    "last_update": "2025-12-06 03:49:25",
    "song": {
      "musicAuthor": "Depeche Mode",
      "musicCover": "https://i.scdn.co/image/ab67616d000048510a7d45a345534966a4ad2c39",
      "musicTitle": "Enjoy The Silence",
      "radio": "Rádio ROCK",
      "startTime": "04:48"
    },
    "recorded_at": "2025-12-06T04:49:26.250876+01:00",
    "raw_valid": true,
    "song_session_id": "2604408d-9323-42f4-8f50-706dece208b5"
  },
  {
    "last_update": "2025-12-06 03:52:25",
    "song": {
      "musicAuthor": "Gladiator",
      "musicCover": "https://static.radia.sk/covers/32/637e2fb2-bf40-4366-b0dc-2df4a2d31541.jpg",
      "musicTitle": "Third Eye",
      "radio": "Rádio ROCK",
      "startTime": "04:52"
    },
    "recorded_at": "2025-12-06T04:52:26.423501+01:00",
    "raw_valid": true,
    "song_session_id": "f57b450c-5455-47bb-9951-698647702957"
  }
]