[
  {
    "listeners": 322,
    "recorded_at": "2025-11-16T02:03:42.993987+01:00",
    "raw_valid": true,
    "song_session_id": "db306438-af76-438e-97b8-7dc2dc43cf8b"
  },
  {
    "listeners": 319,
    "recorded_at": "2025-11-16T02:04:13.024399+01:00",
    "raw_valid": true,
    "song_session_id": "db306438-af76-438e-97b8-7dc2dc43cf8b"
  },
  {
    "listeners": 321,
    "recorded_at": "2025-11-16T02:04:43.045722+01:00",
    "raw_valid": true,
    "song_session_id": "db306438-af76-438e-97b8-7dc2dc43cf8b"
  },
  {
    "listeners": 316,
    "recorded_at": "2025-11-16T02:05:13.076132+01:00",
    "raw_valid": true,
    "song_session_id": "db306438-af76-438e-97b8-7dc2dc43cf8b"
  },
  {
    "listeners": 322,
    "recorded_at": "2025-11-16T02:06:23.873644+01:00",
    "raw_valid": true,
    "song_session_id": "610f851c-6e77-4fe6-80d8-76997dcd0851"
  },
  {
    "listeners": 319,
    "recorded_at": "2025-11-16T02:06:53.875041+01:00",
    "raw_valid": true,
    "song_session_id": "610f851c-6e77-4fe6-80d8-76997dcd0851"
  },
  {
    "listeners": 316,
    "recorded_at": "2025-11-16T02:07:23.877712+01:00",
    "raw_valid": true,
    "song_session_id": "610f851c-6e77-4fe6-80d8-76997dcd0851"
  },
  {
    "listeners": 316,
    "recorded_at": "2025-11-16T02:07:53.879709+01:00",
    "raw_valid": true,
    "song_session_id": "610f851c-6e77-4fe6-80d8-76997dcd0851"
  },
  {
    "listeners": 325,
    "recorded_at": "2025-11-16T02:08:23.887407+01:00",
    "raw_valid": true,
    "song_session_id": "610f851c-6e77-4fe6-80d8-76997dcd0851"
  },
  {
    "listeners": 319,
    "recorded_at": "2025-11-16T02:08:53.888726+01:00",
    "raw_valid": true,
    "song_session_id": "610f851c-6e77-4fe6-80d8-76997dcd0851"
  },
  {
    "listeners": 321,
    "recorded_at": "2025-11-16T02:09:23.892372+01:00",
    "raw_valid": true,
    "song_session_id": "610f851c-6e77-4fe6-80d8-76997dcd0851"
  },
  {
    "listeners": 324,
    "recorded_at": "2025-11-16T02:09:53.893708+01:00",
    "raw_valid": true,
    "song_session_id": "610f851c-6e77-4fe6-80d8-76997dcd0851"
  },
  {
    "listeners": 325,
    "recorded_at": "2025-11-16T02:10:23.894834+01:00",
    "raw_valid": true,
    "song_session_id": "3c7d2111-44e3-479b-85e3-59afe36f8c38"
  },
  {
    "listeners": 315,
    "recorded_at": "2025-11-16T02:10:53.901846+01:00",
    "raw_valid": true,
    "song_session_id": "3c7d2111-44e3-479b-85e3-59afe36f8c38"
  },
  {
    "listeners": 321,
    "recorded_at": "2025-11-16T02:11:23.903013+01:00",
    "raw_valid": true,
    "song_session_id": "3c7d2111-44e3-479b-85e3-59afe36f8c38"
  },
  {
    "listeners": 315,
    "recorded_at": "2025-11-16T02:11:53.917710+01:00",
    "raw_valid": true,
    "song_session_id": "3c7d2111-44e3-479b-85e3-59afe36f8c38"
  },
  {
    "listeners": 316,
    "recorded_at": "2025-11-16T02:12:23.948185+01:00",
    "raw_valid": true,
    "song_session_id": "3c7d2111-44e3-479b-85e3-59afe36f8c38"
  },
  {
    "listeners": 317,
    "recorded_at": "2025-11-16T02:12:53.978628+01:00",
    "raw_valid": true,
    "song_session_id": "3c7d2111-44e3-479b-85e3-59afe36f8c38"
  },
  {
    "listeners": 323,
    "recorded_at": "2025-11-16T02:13:24.005730+01:00",
    "raw_valid": true,
    "song_session_id": "cc1525d1-5a9e-405c-8326-fa5966da2122"
  },
  {
    "listeners": 323,
    "recorded_at": "2025-11-16T02:13:54.029708+01:00",
    "raw_valid": true,
    "song_session_id": "cc1525d1-5a9e-405c-8326-fa5966da2122"
  },
  {
    "listeners": 315,
    "recorded_at": "2025-11-16T02:14:24.060096+01:00",
    "raw_valid": true,
    "song_session_id": "cc1525d1-5a9e-405c-8326-fa5966da2122"
  },
  {
    "listeners": 319,
    "recorded_at": "2025-11-16T02:14:54.077726+01:00",
    "raw_valid": true,
    "song_session_id": "cc1525d1-5a9e-405c-8326-fa5966da2122"
  },
  {
    "listeners": 325,
    "recorded_at": "2025-11-16T02:15:24.108155+01:00",
    "raw_valid": true,
    "song_session_id": "cc1525d1-5a9e-405c-8326-fa5966da2122"
  },
  {
    "listeners": 318,
    "recorded_at": "2025-11-16T02:15:54.138606+01:00",
    "raw_valid": true,
    "song_session_id": "cc1525d1-5a9e-405c-8326-fa5966da2122"
  },
  {
    "listeners": 324,
    "recorded_at": "2025-11-16T02:16:24.141733+01:00",
    "raw_valid": true,
    "song_session_id": "cc1525d1-5a9e-405c-8326-fa5966da2122"
  },
  {
    "listeners": 323,
    "recorded_at": "2025-11-16T02:16:54.172181+01:00",
    "raw_valid": true,
    "song_session_id": "cc1525d1-5a9e-405c-8326-fa5966da2122"
  },
  {
    "listeners": 318,
    "recorded_at": "2025-11-16T02:17:24.202804+01:00",
    "raw_valid": true,
    "song_session_id": "cc1525d1-5a9e-405c-8326-fa5966da2122"
  },
  {
    "listeners": 317,
    "recorded_at": "2025-11-16T02:17:54.205940+01:00",
    "raw_valid": true,
    "song_session_id": "cc1525d1-5a9e-405c-8326-fa5966da2122"
  },
  {
    "listeners": 315,
    "recorded_at": "2025-11-16T02:18:24.236439+01:00",
    "raw_valid": true,
    "song_session_id": "cc1525d1-5a9e-405c-8326-fa5966da2122"
  },
  {
    "listeners": 317,
    "recorded_at": "2025-11-16T02:18:54.244141+01:00",
    "raw_valid": true,
    "song_session_id": "cc1525d1-5a9e-405c-8326-fa5966da2122"
  },
  {
    "listeners": 316,
    "recorded_at": "2025-11-16T02:20:05.267352+01:00",
    "raw_valid": true,
    "song_session_id": "cc1525d1-5a9e-405c-8326-fa5966da2122"
  },
  {
    "listeners": 325,
    "recorded_at": "2025-11-16T02:20:35.269173+01:00",
    "raw_valid": true,
    "song_session_id": "54d80046-9727-43e5-a0cd-2f674f4bb058"
  },
  {
    "listeners": 322,
    "recorded_at": "2025-11-16T02:21:05.279438+01:00",
    "raw_valid": true,
    "song_session_id": "54d80046-9727-43e5-a0cd-2f674f4bb058"
  },
  {
    "listeners": 318,
    "recorded_at": "2025-11-16T02:21:35.281527+01:00",
    "raw_valid": true,
    "song_session_id": "54d80046-9727-43e5-a0cd-2f674f4bb058"
  },
  {
    "listeners": 318,
    "recorded_at": "2025-11-16T02:22:05.288609+01:00",
    "raw_valid": true,
    "song_session_id": "54d80046-9727-43e5-a0cd-2f674f4bb058"
  },
  {
    "listeners": 317,
    "recorded_at": "2025-11-16T02:22:35.289992+01:00",
    "raw_valid": true,
    "song_session_id": "54d80046-9727-43e5-a0cd-2f674f4bb058"
  },
  {
    "listeners": 324,
    "recorded_at": "2025-11-16T02:23:05.291386+01:00",
    "raw_valid": true,
    "song_session_id": "54d80046-9727-43e5-a0cd-2f674f4bb058"
  },
  {
    "listeners": 322,
    "recorded_at": "2025-11-16T02:23:35.292779+01:00",
    "raw_valid": true,
    "song_session_id": "daaede83-c9d8-4646-8241-bf62f41f5273"
  },
  {
    "listeners": 315,
    "recorded_at": "2025-11-16T02:24:05.295736+01:00",
    "raw_valid": true,
    "song_session_id": "daaede83-c9d8-4646-8241-bf62f41f5273"
  },
  {
    "listeners": 317,
    "recorded_at": "2025-11-16T02:24:35.297645+01:00",
    "raw_valid": true,
    "song_session_id": "daaede83-c9d8-4646-8241-bf62f41f5273"
  },
  {
    "listeners": 325,
    "recorded_at": "2025-11-16T02:25:05.299112+01:00",
    "raw_valid": true,
    "song_session_id": "daaede83-c9d8-4646-8241-bf62f41f5273"
  },
  {
    "listeners": 324,
    "recorded_at": "2025-11-16T02:25:35.317681+01:00",
    "raw_valid": true,
    "song_session_id": "daaede83-c9d8-4646-8241-bf62f41f5273"
  },
  {
    "listeners": 315,
    "recorded_at": "2025-11-16T02:26:05.348185+01:00",
    "raw_valid": true,
    "song_session_id": "daaede83-c9d8-4646-8241-bf62f41f5273"
  },
  {
    "listeners": 321,
    "recorded_at": "2025-11-16T02:26:35.378564+01:00",
    "raw_valid": true,
    "song_session_id": "daaede83-c9d8-4646-8241-bf62f41f5273"
  },
  {
    "listeners": 319,
    "recorded_at": "2025-11-16T02:27:05.405676+01:00",
    "raw_valid": true,
    "song_session_id": "daaede83-c9d8-4646-8241-bf62f41f5273"
  },
  {
    "listeners": 323,
    "recorded_at": "2025-11-16T02:27:35.421689+01:00",
    "raw_valid": true,
    "song_session_id": "d052a38a-97c5-4ed6-a114-f070a36e7de9"
  },
  {
    "listeners": 323,
    "recorded_at": "2025-11-16T02:28:05.437711+01:00",
    "raw_valid": true,
    "song_session_id": "d052a38a-97c5-4ed6-a114-f070a36e7de9"
  },
  {
    "listeners": 317,
    "recorded_at": "2025-11-16T02:28:35.449526+01:00",
    "raw_valid": true,
    "song_session_id": "d052a38a-97c5-4ed6-a114-f070a36e7de9"
  },
  {
    "listeners": 320,
    "recorded_at": "2025-11-16T02:29:05.469653+01:00",
    "raw_valid": true,
    "song_session_id": "d052a38a-97c5-4ed6-a114-f070a36e7de9"
  },
  {
    "listeners": 320,
    "recorded_at": "2025-11-16T02:29:35.500033+01:00",
    "raw_valid": true,
    "song_session_id": "d052a38a-97c5-4ed6-a114-f070a36e7de9"
  },
  {
    "listeners": 322,
    "recorded_at": "2025-11-16T02:30:05.501744+01:00",
    "raw_valid": true,
    "song_session_id": "d052a38a-97c5-4ed6-a114-f070a36e7de9"
  },
  {
    "listeners": 320,
    "recorded_at": "2025-11-16T02:30:35.532216+01:00",
    "raw_valid": true,
    "song_session_id": "d052a38a-97c5-4ed6-a114-f070a36e7de9"
  },
  {
    "listeners": 316,
    "recorded_at": "2025-11-16T02:31:05.562753+01:00",
    "raw_valid": true,
    "song_session_id": "d052a38a-97c5-4ed6-a114-f070a36e7de9"
  },
  {
    "listeners": 320,
    "recorded_at": "2025-11-16T02:31:35.581664+01:00",
    "raw_valid": true,
    "song_session_id": "75c75e2a-389f-4952-8953-bff3804835ae"
  },
  {
    "listeners": 315,
    "recorded_at": "2025-11-16T02:32:05.612054+01:00",
    "raw_valid": true,
    "song_session_id": "75c75e2a-389f-4952-8953-bff3804835ae"
  },
  {
    "listeners": 320,
    "recorded_at": "2025-11-16T02:32:35.642414+01:00",
    "raw_valid": true,
    "song_session_id": "75c75e2a-389f-4952-8953-bff3804835ae"
  },
  {
    "listeners": 320,
    "recorded_at": "2025-11-16T02:33:46.062325+01:00",
    "raw_valid": true,
    "song_session_id": "75c75e2a-389f-4952-8953-bff3804835ae"
  },
  {
    "listeners": 322,
    "recorded_at": "2025-11-16T02:34:16.063375+01:00",
    "raw_valid": true,
    "song_session_id": "75c75e2a-389f-4952-8953-bff3804835ae"
  },
  {
    "listeners": 315,
    "recorded_at": "2025-11-16T02:34:46.069726+01:00",
    "raw_valid": true,
    "song_session_id": "a1e3666a-5b1b-44cf-83c1-1b46af0b11ee"
  },
  {
    "listeners": 322,
    "recorded_at": "2025-11-16T02:35:16.071369+01:00",
    "raw_valid": true,
    "song_session_id": "a1e3666a-5b1b-44cf-83c1-1b46af0b11ee"
  },
  {
    "listeners": 317,
    "recorded_at": "2025-11-16T02:35:46.077311+01:00",
    "raw_valid": true,
    "song_session_id": "a1e3666a-5b1b-44cf-83c1-1b46af0b11ee"
  },
  {
    "listeners": 319,
    "recorded_at": "2025-11-16T02:36:16.078396+01:00",
    "raw_valid": true,
    "song_session_id": "a1e3666a-5b1b-44cf-83c1-1b46af0b11ee"
  },
  {
    "listeners": 317,
    "recorded_at": "2025-11-16T02:36:46.080872+01:00",
    "raw_valid": true,
    "song_session_id": "a1e3666a-5b1b-44cf-83c1-1b46af0b11ee"
  },
  {
    "listeners": 325,
    "recorded_at": "2025-11-16T02:37:16.081866+01:00",
    "raw_valid": true,
    "song_session_id": "a1e3666a-5b1b-44cf-83c1-1b46af0b11ee"
  },
  {
    "listeners": 320,
    "recorded_at": "2025-11-16T02:37:46.092397+01:00",
    "raw_valid": true,
    "song_session_id": "a1e3666a-5b1b-44cf-83c1-1b46af0b11ee"
  },
  {
    "listeners": 324,
    "recorded_at": "2025-11-16T02:38:16.093779+01:00",
    "raw_valid": true,
    "song_session_id": "a1e3666a-5b1b-44cf-83c1-1b46af0b11ee"
  },
  {
    "listeners": 324,
    "recorded_at": "2025-11-16T02:38:46.095434+01:00",
    "raw_valid": true,
    "song_session_id": "8c407c8f-b409-4a96-bc4a-58725a8dea82"
  },
  {
    "listeners": 324,
    "recorded_at": "2025-11-16T02:39:16.116401+01:00",
    "raw_valid": true,
    "song_session_id": "8c407c8f-b409-4a96-bc4a-58725a8dea82"
  },
  {
    "listeners": 325,
    "recorded_at": "2025-11-16T02:39:46.146816+01:00",
    "raw_valid": true,
    "song_session_id": "8c407c8f-b409-4a96-bc4a-58725a8dea82"
  },
  {
    "listeners": 323,
    "recorded_at": "2025-11-16T02:40:16.177191+01:00",
    "raw_valid": true,
    "song_session_id": "8c407c8f-b409-4a96-bc4a-58725a8dea82"
  },
  {
    "listeners": 317,
    "recorded_at": "2025-11-16T02:40:46.206755+01:00",
    "raw_valid": true,
    "song_session_id": "8c407c8f-b409-4a96-bc4a-58725a8dea82"
  },
  {
    "listeners": 319,
    "recorded_at": "2025-11-16T02:41:16.221671+01:00",
    "raw_valid": true,
    "song_session_id": "8c407c8f-b409-4a96-bc4a-58725a8dea82"
  },
  {
    "listeners": 319,
    "recorded_at": "2025-11-16T02:41:46.243050+01:00",
    "raw_valid": true,
    "song_session_id": "8c407c8f-b409-4a96-bc4a-58725a8dea82"
  },
  {
    "listeners": 322,
    "recorded_at": "2025-11-16T02:42:16.253718+01:00",
    "raw_valid": true,
    "song_session_id": "8c407c8f-b409-4a96-bc4a-58725a8dea82"
  },
  {
    "listeners": 318,
    "recorded_at": "2025-11-16T02:42:46.284121+01:00",
    "raw_valid": true,
    "song_session_id": "8c407c8f-b409-4a96-bc4a-58725a8dea82"
  },
  {
    "listeners": 321,
    "recorded_at": "2025-11-16T02:43:16.314587+01:00",
    "raw_valid": true,
    "song_session_id": "8c407c8f-b409-4a96-bc4a-58725a8dea82"
  },
  {
    "listeners": 318,
    "recorded_at": "2025-11-16T02:43:46.317802+01:00",
    "raw_valid": true,
    "song_session_id": "68da1e1a-af56-4c83-be97-7c12ffa8b73f"
  },
  {
    "listeners": 319,
    "recorded_at": "2025-11-16T02:44:16.348238+01:00",
    "raw_valid": true,
    "song_session_id": "68da1e1a-af56-4c83-be97-7c12ffa8b73f"
  },
  {
    "listeners": 319,
    "recorded_at": "2025-11-16T02:44:46.378691+01:00",
    "raw_valid": true,
    "song_session_id": "68da1e1a-af56-4c83-be97-7c12ffa8b73f"
  },
  {
    "listeners": 316,
    "recorded_at": "2025-11-16T02:45:16.389780+01:00",
    "raw_valid": true,
    "song_session_id": "68da1e1a-af56-4c83-be97-7c12ffa8b73f"
  },
  {
    "listeners": 324,
    "recorded_at": "2025-11-16T02:45:46.397015+01:00",
    "raw_valid": true,
    "song_session_id": "68da1e1a-af56-4c83-be97-7c12ffa8b73f"
  },
  {
    "listeners": 321,
    "recorded_at": "2025-11-16T02:46:16.409692+01:00",
    "raw_valid": true,
    "song_session_id": "68da1e1a-af56-4c83-be97-7c12ffa8b73f"
  },
  {
    "listeners": 318,
    "recorded_at": "2025-11-16T02:47:27.444750+01:00",
    "raw_valid": true,
    "song_session_id": "184e571f-4ee5-4bf2-9b96-ddc4cc0292f4"
  },
  {
    "listeners": 315,
    "recorded_at": "2025-11-16T02:47:57.446303+01:00",
    "raw_valid": true,
    "song_session_id": "184e571f-4ee5-4bf2-9b96-ddc4cc0292f4"
  },
  {
    "listeners": 321,
    "recorded_at": "2025-11-16T02:48:27.452520+01:00",
    "raw_valid": true,
    "song_session_id": "184e571f-4ee5-4bf2-9b96-ddc4cc0292f4"
  },
  {
    "listeners": 323,
    "recorded_at": "2025-11-16T02:48:57.454383+01:00",
    "raw_valid": true,
    "song_session_id": "184e571f-4ee5-4bf2-9b96-ddc4cc0292f4"
  },
  {
    "listeners": 325,
    "recorded_at": "2025-11-16T02:49:27.462555+01:00",
    "raw_valid": true,
    "song_session_id": "184e571f-4ee5-4bf2-9b96-ddc4cc0292f4"
  },
  {
    "listeners": 316,
    "recorded_at": "2025-11-16T02:49:57.465790+01:00",
    "raw_valid": true,
    "song_session_id": "184e571f-4ee5-4bf2-9b96-ddc4cc0292f4"
  },
  {
    "listeners": 325,
    "recorded_at": "2025-11-16T02:50:27.470039+01:00",
    "raw_valid": true,
    "song_session_id": "184e571f-4ee5-4bf2-9b96-ddc4cc0292f4"
  },
  {
    "listeners": 324,
    "recorded_at": "2025-11-16T02:50:57.472712+01:00",
    "raw_valid": true,
    "song_session_id": "184e571f-4ee5-4bf2-9b96-ddc4cc0292f4"
  },
  {
    "listeners": 321,
    "recorded_at": "2025-11-16T02:51:27.481816+01:00",
    "raw_valid": true,
    "song_session_id": "184e571f-4ee5-4bf2-9b96-ddc4cc0292f4"
  },
  {
    "listeners": 317,
    "recorded_at": "2025-11-16T02:51:57.484126+01:00",
    "raw_valid": true,
    "song_session_id": "49652bba-415a-4d1a-bd80-96a1ed307759"
  },
  {
    "listeners": 322,
    "recorded_at": "2025-11-16T02:52:27.486200+01:00",
    "raw_valid": true,
    "song_session_id": "49652bba-415a-4d1a-bd80-96a1ed307759"
  },
  {
    "listeners": 320,
    "recorded_at": "2025-11-16T02:52:57.516619+01:00",
    "raw_valid": true,
    "song_session_id": "49652bba-415a-4d1a-bd80-96a1ed307759"
  },
  {
    "listeners": 321,
    "recorded_at": "2025-11-16T02:53:27.541719+01:00",
    "raw_valid": true,
    "song_session_id": "49652bba-415a-4d1a-bd80-96a1ed307759"
  },
  {
    "listeners": 324,
    "recorded_at": "2025-11-16T02:53:57.565768+01:00",
    "raw_valid": true,
    "song_session_id": "49652bba-415a-4d1a-bd80-96a1ed307759"
  },
  {
    "listeners": 315,
    "recorded_at": "2025-11-16T02:54:27.596225+01:00",
    "raw_valid": true,
    "song_session_id": "49652bba-415a-4d1a-bd80-96a1ed307759"
  },
  {
    "listeners": 317,
    "recorded_at": "2025-11-16T02:54:57.605831+01:00",
    "raw_valid": true,
    "song_session_id": "49652bba-415a-4d1a-bd80-96a1ed307759"
  },
  {
    "listeners": 317,
    "recorded_at": "2025-11-16T02:55:27.630540+01:00",
    "raw_valid": true,
    "song_session_id": "49652bba-415a-4d1a-bd80-96a1ed307759"
  },
  {
    "listeners": 316,
    "recorded_at": "2025-11-16T02:55:57.660926+01:00",
    "raw_valid": true,
    "song_session_id": "a70b3fea-8149-4a04-8216-6b0700644f35"
  },
  {
    "listeners": 325,
    "recorded_at": "2025-11-16T02:56:27.669669+01:00",
    "raw_valid": true,
    "song_session_id": "a70b3fea-8149-4a04-8216-6b0700644f35"
  },
  {
    "listeners": 318,
    "recorded_at": "2025-11-16T02:56:57.700040+01:00",
    "raw_valid": true,
    "song_session_id": "a70b3fea-8149-4a04-8216-6b0700644f35"
  },
  {
    "listeners": 317,
    "recorded_at": "2025-11-16T02:57:27.730499+01:00",
    "raw_valid": true,
    "song_session_id": "a70b3fea-8149-4a04-8216-6b0700644f35"
  },
  {
    "listeners": 322,
    "recorded_at": "2025-11-16T02:57:57.733690+01:00",
    "raw_valid": true,
    "song_session_id": "a70b3fea-8149-4a04-8216-6b0700644f35"
  },
  {
    "listeners": 315,
    "recorded_at": "2025-11-16T02:58:27.764364+01:00",
    "raw_valid": true,
    "song_session_id": "a70b3fea-8149-4a04-8216-6b0700644f35"
  },
  {
    "listeners": 315,
    "recorded_at": "2025-11-16T02:58:57.789701+01:00",
    "raw_valid": true,
    "song_session_id": "a70b3fea-8149-4a04-8216-6b0700644f35"
  },
  {
    "listeners": 317,
    "recorded_at": "2025-11-16T02:59:27.805668+01:00",
    "raw_valid": true,
    "song_session_id": "a70b3fea-8149-4a04-8216-6b0700644f35"
  },
  {
    "listeners": 317,
    "recorded_at": "2025-11-16T02:59:57.813713+01:00",
    "raw_valid": true,
    "song_session_id": "41b99d8c-40c7-4fd7-9830-09126c68d7b9"
  },
  {
    "listeners": 316,
    "recorded_at": "2025-11-16T03:01:08.072872+01:00",
    "raw_valid": true,
    "song_session_id": "41b99d8c-40c7-4fd7-9830-09126c68d7b9"
  },
  {
    "listeners": 320,
    "recorded_at": "2025-11-16T03:01:38.074336+01:00",
    "raw_valid": true,
    "song_session_id": "41b99d8c-40c7-4fd7-9830-09126c68d7b9"
  },
  {
    "listeners": 317,
    "recorded_at": "2025-11-16T03:02:08.082011+01:00",
    "raw_valid": true,
    "song_session_id": "41b99d8c-40c7-4fd7-9830-09126c68d7b9"
  },
  {
    "listeners": 325,
    "recorded_at": "2025-11-16T03:02:38.082769+01:00",
    "raw_valid": true,
    "song_session_id": "1e5cc7da-a7c1-4d71-aaa8-1a4b5a0f1d9c"
  },
  {
    "listeners": 321,
    "recorded_at": "2025-11-16T03:03:08.087813+01:00",
    "raw_valid": true,
    "song_session_id": "1e5cc7da-a7c1-4d71-aaa8-1a4b5a0f1d9c"
  },
  {
    "listeners": 322,
    "recorded_at": "2025-11-16T03:03:38.089034+01:00",
    "raw_valid": true,
    "song_session_id": "1e5cc7da-a7c1-4d71-aaa8-1a4b5a0f1d9c"
  },
  {
    "listeners": 317,
    "recorded_at": "2025-11-16T03:04:08.091786+01:00",
    "raw_valid": true,
    "song_session_id": "1e5cc7da-a7c1-4d71-aaa8-1a4b5a0f1d9c"
  },
  {
    "listeners": 316,
    "recorded_at": "2025-11-16T03:04:38.094213+01:00",
    "raw_valid": true,
    "song_session_id": "1e5cc7da-a7c1-4d71-aaa8-1a4b5a0f1d9c"
  },
  {
    "listeners": 317,
    "recorded_at": "2025-11-16T03:05:08.104086+01:00",
    "raw_valid": true,
    "song_session_id": "1e5cc7da-a7c1-4d71-aaa8-1a4b5a0f1d9c"
  },
  {
    "listeners": 320,
    "recorded_at": "2025-11-16T03:05:38.104847+01:00",
    "raw_valid": true,
    "song_session_id": "1e5cc7da-a7c1-4d71-aaa8-1a4b5a0f1d9c"
  },
  {
    "listeners": 318,
    "recorded_at": "2025-11-16T03:06:08.106193+01:00",
    "raw_valid": true,
    "song_session_id": "1e5cc7da-a7c1-4d71-aaa8-1a4b5a0f1d9c"
  },
  {
    "listeners": 321,
    "recorded_at": "2025-11-16T03:06:38.136641+01:00",
    "raw_valid": true,
    "song_session_id": "b0cd040f-9463-47ca-9ade-ea1ac96e0ea8"
  },
  {
    "listeners": 322,
    "recorded_at": "2025-11-16T03:07:08.165686+01:00",
    "raw_valid": true,
    "song_session_id": "b0cd040f-9463-47ca-9ade-ea1ac96e0ea8"
  },
  {
    "listeners": 320,
    "recorded_at": "2025-11-16T03:07:38.196092+01:00",
    "raw_valid": true,
    "song_session_id": "b0cd040f-9463-47ca-9ade-ea1ac96e0ea8"
  },
  {
    "listeners": 321,
    "recorded_at": "2025-11-16T03:08:08.203441+01:00",
    "raw_valid": true,
    "song_session_id": "b0cd040f-9463-47ca-9ade-ea1ac96e0ea8"
  },
  {
    "listeners": 318,
    "recorded_at": "2025-11-16T03:08:38.229737+01:00",
    "raw_valid": true,
    "song_session_id": "b0cd040f-9463-47ca-9ade-ea1ac96e0ea8"
  },
  {
    "listeners": 325,
    "recorded_at": "2025-11-16T03:09:08.253661+01:00",
    "raw_valid": true,
    "song_session_id": "b0cd040f-9463-47ca-9ade-ea1ac96e0ea8"
  },
  {
    "listeners": 317,
    "recorded_at": "2025-11-16T03:09:38.261560+01:00",
    "raw_valid": true,
    "song_session_id": "c349d181-fde9-4feb-b7a4-50b0a464edd2"
  },
  {
    "listeners": 323,
    "recorded_at": "2025-11-16T03:10:08.291962+01:00",
    "raw_valid": true,
    "song_session_id": "c349d181-fde9-4feb-b7a4-50b0a464edd2"
  },
  {
    "listeners": 322,
    "recorded_at": "2025-11-16T03:10:38.301702+01:00",
    "raw_valid": true,
    "song_session_id": "c349d181-fde9-4feb-b7a4-50b0a464edd2"
  },
  {
    "listeners": 317,
    "recorded_at": "2025-11-16T03:11:08.317699+01:00",
    "raw_valid": true,
    "song_session_id": "c349d181-fde9-4feb-b7a4-50b0a464edd2"
  },
  {
    "listeners": 323,
    "recorded_at": "2025-11-16T03:11:38.328178+01:00",
    "raw_valid": true,
    "song_session_id": "c349d181-fde9-4feb-b7a4-50b0a464edd2"
  },
  {
    "listeners": 319,
    "recorded_at": "2025-11-16T03:12:08.341694+01:00",
    "raw_valid": true,
    "song_session_id": "c349d181-fde9-4feb-b7a4-50b0a464edd2"
  },
  {
    "listeners": 319,
    "recorded_at": "2025-11-16T03:12:38.372207+01:00",
    "raw_valid": true,
    "song_session_id": "53b41fb0-aaea-48fb-a498-21b94fc7d700"
  },
  {
    "listeners": 320,
    "recorded_at": "2025-11-16T03:13:08.402689+01:00",
    "raw_valid": true,
    "song_session_id": "53b41fb0-aaea-48fb-a498-21b94fc7d700"
  },
  {
    "listeners": 321,
    "recorded_at": "2025-11-16T03:13:38.405738+01:00",
    "raw_valid": true,
    "song_session_id": "53b41fb0-aaea-48fb-a498-21b94fc7d700"
  },
  {
    "listeners": 319,
    "recorded_at": "2025-11-16T03:14:48.597814+01:00",
    "raw_valid": true,
    "song_session_id": "53b41fb0-aaea-48fb-a498-21b94fc7d700"
  },
  {
    "listeners": 321,
    "recorded_at": "2025-11-16T03:15:18.598949+01:00",
    "raw_valid": true,
    "song_session_id": "53b41fb0-aaea-48fb-a498-21b94fc7d700"
  },
  {
    "listeners": 316,
    "recorded_at": "2025-11-16T03:15:48.607908+01:00",
    "raw_valid": true,
    "song_session_id": "53b41fb0-aaea-48fb-a498-21b94fc7d700"
  },
  {
    "listeners": 325,
    "recorded_at": "2025-11-16T03:16:18.609713+01:00",
    "raw_valid": true,
    "song_session_id": "53b41fb0-aaea-48fb-a498-21b94fc7d700"
  },
  {
    "listeners": 319,
    "recorded_at": "2025-11-16T03:16:48.616566+01:00",
    "raw_valid": true,
    "song_session_id": "53b41fb0-aaea-48fb-a498-21b94fc7d700"
  },
  {
    "listeners": 321,
    "recorded_at": "2025-11-16T03:17:18.617884+01:00",
    "raw_valid": true,
    "song_session_id": "53b41fb0-aaea-48fb-a498-21b94fc7d700"
  },
  {
    "listeners": 319,
    "recorded_at": "2025-11-16T03:17:48.620775+01:00",
    "raw_valid": true,
    "song_session_id": "dc783a75-3581-479a-80ae-220ab77e7ea1"
  },
  {
    "listeners": 320,
    "recorded_at": "2025-11-16T03:18:18.622145+01:00",
    "raw_valid": true,
    "song_session_id": "dc783a75-3581-479a-80ae-220ab77e7ea1"
  },
  {
    "listeners": 324,
    "recorded_at": "2025-11-16T03:18:48.624599+01:00",
    "raw_valid": true,
    "song_session_id": "dc783a75-3581-479a-80ae-220ab77e7ea1"
  },
  {
    "listeners": 321,
    "recorded_at": "2025-11-16T03:19:18.625155+01:00",
    "raw_valid": true,
    "song_session_id": "dc783a75-3581-479a-80ae-220ab77e7ea1"
  },
  {
    "listeners": 322,
    "recorded_at": "2025-11-16T03:19:48.625889+01:00",
    "raw_valid": true,
    "song_session_id": "72b11502-487f-4685-bda0-ee8d23746e18"
  },
  {
    "listeners": 317,
    "recorded_at": "2025-11-16T03:20:18.653676+01:00",
    "raw_valid": true,
    "song_session_id": "72b11502-487f-4685-bda0-ee8d23746e18"
  },
  {
    "listeners": 323,
    "recorded_at": "2025-11-16T03:20:48.661669+01:00",
    "raw_valid": true,
    "song_session_id": "72b11502-487f-4685-bda0-ee8d23746e18"
  },
  {
    "listeners": 321,
    "recorded_at": "2025-11-16T03:21:18.665330+01:00",
    "raw_valid": true,
    "song_session_id": "72b11502-487f-4685-bda0-ee8d23746e18"
  },
  {
    "listeners": 323,
    "recorded_at": "2025-11-16T03:21:48.695830+01:00",
    "raw_valid": true,
    "song_session_id": "72b11502-487f-4685-bda0-ee8d23746e18"
  },
  {
    "listeners": 323,
    "recorded_at": "2025-11-16T03:22:18.717682+01:00",
    "raw_valid": true,
    "song_session_id": "72b11502-487f-4685-bda0-ee8d23746e18"
  },
  {
    "listeners": 324,
    "recorded_at": "2025-11-16T03:22:48.748071+01:00",
    "raw_valid": true,
    "song_session_id": "c5167959-eba9-4eb9-a57d-f4b8c84fa92b"
  },
  {
    "listeners": 322,
    "recorded_at": "2025-11-16T03:23:18.778550+01:00",
    "raw_valid": true,
    "song_session_id": "c5167959-eba9-4eb9-a57d-f4b8c84fa92b"
  },
  {
    "listeners": 321,
    "recorded_at": "2025-11-16T03:23:48.804399+01:00",
    "raw_valid": true,
    "song_session_id": "c5167959-eba9-4eb9-a57d-f4b8c84fa92b"
  },
  {
    "listeners": 321,
    "recorded_at": "2025-11-16T03:24:18.813721+01:00",
    "raw_valid": true,
    "song_session_id": "c5167959-eba9-4eb9-a57d-f4b8c84fa92b"
  },
  {
    "listeners": 323,
    "recorded_at": "2025-11-16T03:24:48.844170+01:00",
    "raw_valid": true,
    "song_session_id": "c5167959-eba9-4eb9-a57d-f4b8c84fa92b"
  },
  {
    "listeners": 321,
    "recorded_at": "2025-11-16T03:25:18.853723+01:00",
    "raw_valid": true,
    "song_session_id": "c5167959-eba9-4eb9-a57d-f4b8c84fa92b"
  },
  {
    "listeners": 323,
    "recorded_at": "2025-11-16T03:25:48.884143+01:00",
    "raw_valid": true,
    "song_session_id": "263a6507-6c48-4140-91a1-691a2113ff52"
  },
  {
    "listeners": 323,
    "recorded_at": "2025-11-16T03:26:18.914618+01:00",
    "raw_valid": true,
    "song_session_id": "263a6507-6c48-4140-91a1-691a2113ff52"
  },
  {
    "listeners": 321,
    "recorded_at": "2025-11-16T03:26:48.917726+01:00",
    "raw_valid": true,
    "song_session_id": "263a6507-6c48-4140-91a1-691a2113ff52"
  },
  {
    "listeners": 324,
    "recorded_at": "2025-11-16T03:27:18.940809+01:00",
    "raw_valid": true,
    "song_session_id": "263a6507-6c48-4140-91a1-691a2113ff52"
  },
  {
    "listeners": 325,
    "recorded_at": "2025-11-16T03:28:29.634443+01:00",
    "raw_valid": true,
    "song_session_id": "263a6507-6c48-4140-91a1-691a2113ff52"
  },
  {
    "listeners": 325,
    "recorded_at": "2025-11-16T03:28:59.635671+01:00",
    "raw_valid": true,
    "song_session_id": "559f73b0-0a80-4bcd-b642-e705bea74ea8"
  },
  {
    "listeners": 315,
    "recorded_at": "2025-11-16T03:29:29.644277+01:00",
    "raw_valid": true,
    "song_session_id": "559f73b0-0a80-4bcd-b642-e705bea74ea8"
  },
  {
    "listeners": 319,
    "recorded_at": "2025-11-16T03:29:59.645621+01:00",
    "raw_valid": true,
    "song_session_id": "559f73b0-0a80-4bcd-b642-e705bea74ea8"
  },
  {
    "listeners": 323,
    "recorded_at": "2025-11-16T03:30:29.653191+01:00",
    "raw_valid": true,
    "song_session_id": "559f73b0-0a80-4bcd-b642-e705bea74ea8"
  },
  {
    "listeners": 323,
    "recorded_at": "2025-11-16T03:30:59.655045+01:00",
    "raw_valid": true,
    "song_session_id": "559f73b0-0a80-4bcd-b642-e705bea74ea8"
  },
  {
    "listeners": 316,
    "recorded_at": "2025-11-16T03:31:29.659120+01:00",
    "raw_valid": true,
    "song_session_id": "559f73b0-0a80-4bcd-b642-e705bea74ea8"
  },
  {
    "listeners": 315,
    "recorded_at": "2025-11-16T03:31:59.661177+01:00",
    "raw_valid": true,
    "song_session_id": "559f73b0-0a80-4bcd-b642-e705bea74ea8"
  },
  {
    "listeners": 318,
    "recorded_at": "2025-11-16T03:32:29.663167+01:00",
    "raw_valid": true,
    "song_session_id": "559f73b0-0a80-4bcd-b642-e705bea74ea8"
  },
  {
    "listeners": 322,
    "recorded_at": "2025-11-16T03:32:59.664351+01:00",
    "raw_valid": true,
    "song_session_id": "c1578ebf-5a35-456b-9b74-225d5c317daa"
  },
  {
    "listeners": 315,
    "recorded_at": "2025-11-16T03:33:29.666284+01:00",
    "raw_valid": true,
    "song_session_id": "c1578ebf-5a35-456b-9b74-225d5c317daa"
  },
  {
    "listeners": 315,
    "recorded_at": "2025-11-16T03:33:59.696918+01:00",
    "raw_valid": true,
    "song_session_id": "c1578ebf-5a35-456b-9b74-225d5c317daa"
  },
  {
    "listeners": 322,
    "recorded_at": "2025-11-16T03:34:29.727544+01:00",
    "raw_valid": true,
    "song_session_id": "c1578ebf-5a35-456b-9b74-225d5c317daa"
  },
  {
    "listeners": 319,
    "recorded_at": "2025-11-16T03:34:59.757984+01:00",
    "raw_valid": true,
    "song_session_id": "c1578ebf-5a35-456b-9b74-225d5c317daa"
  },
  {
    "listeners": 318,
    "recorded_at": "2025-11-16T03:35:29.788693+01:00",
    "raw_valid": true,
    "song_session_id": "c1578ebf-5a35-456b-9b74-225d5c317daa"
  },
  {
    "listeners": 324,
    "recorded_at": "2025-11-16T03:35:59.805715+01:00",
    "raw_valid": true,
    "song_session_id": "c1578ebf-5a35-456b-9b74-225d5c317daa"
  },
  {
    "listeners": 315,
    "recorded_at": "2025-11-16T03:36:29.831174+01:00",
    "raw_valid": true,
    "song_session_id": "c1578ebf-5a35-456b-9b74-225d5c317daa"
  },
  {
    "listeners": 318,
    "recorded_at": "2025-11-16T03:36:59.862027+01:00",
    "raw_valid": true,
    "song_session_id": "81869dbe-dc99-419f-9955-c1dc7711a864"
  },
  {
    "listeners": 317,
    "recorded_at": "2025-11-16T03:37:29.892434+01:00",
    "raw_valid": true,
    "song_session_id": "81869dbe-dc99-419f-9955-c1dc7711a864"
  },
  {
    "listeners": 321,
    "recorded_at": "2025-11-16T03:37:59.922820+01:00",
    "raw_valid": true,
    "song_session_id": "81869dbe-dc99-419f-9955-c1dc7711a864"
  },
  {
    "listeners": 318,
    "recorded_at": "2025-11-16T03:38:29.949670+01:00",
    "raw_valid": true,
    "song_session_id": "81869dbe-dc99-419f-9955-c1dc7711a864"
  },
  {
    "listeners": 317,
    "recorded_at": "2025-11-16T03:38:59.980079+01:00",
    "raw_valid": true,
    "song_session_id": "81869dbe-dc99-419f-9955-c1dc7711a864"
  },
  {
    "listeners": 321,
    "recorded_at": "2025-11-16T03:39:29.981694+01:00",
    "raw_valid": true,
    "song_session_id": "ea7f4368-5728-400a-b142-4dcad3f451bf"
  },
  {
    "listeners": 317,
    "recorded_at": "2025-11-16T03:40:00.012167+01:00",
    "raw_valid": true,
    "song_session_id": "ea7f4368-5728-400a-b142-4dcad3f451bf"
  },
  {
    "listeners": 325,
    "recorded_at": "2025-11-16T03:40:30.042606+01:00",
    "raw_valid": true,
    "song_session_id": "ea7f4368-5728-400a-b142-4dcad3f451bf"
  },
  {
    "listeners": 316,
    "recorded_at": "2025-11-16T03:41:00.073138+01:00",
    "raw_valid": true,
    "song_session_id": "ea7f4368-5728-400a-b142-4dcad3f451bf"
  },
  {
    "listeners": 315,
    "recorded_at": "2025-11-16T03:42:11.105366+01:00",
    "raw_valid": true,
    "song_session_id": "ea7f4368-5728-400a-b142-4dcad3f451bf"
  },
  {
    "listeners": 320,
    "recorded_at": "2025-11-16T03:42:41.108706+01:00",
    "raw_valid": true,
    "song_session_id": "ea7f4368-5728-400a-b142-4dcad3f451bf"
  },
  {
    "listeners": 324,
    "recorded_at": "2025-11-16T03:43:11.116624+01:00",
    "raw_valid": true,
    "song_session_id": "ea7f4368-5728-400a-b142-4dcad3f451bf"
  },
  {
    "listeners": 319,
    "recorded_at": "2025-11-16T03:43:41.118008+01:00",
    "raw_valid": true,
    "song_session_id": "ea7f4368-5728-400a-b142-4dcad3f451bf"
  },
  {
    "listeners": 324,
    "recorded_at": "2025-11-16T03:44:11.124059+01:00",
    "raw_valid": true,
    "song_session_id": "8b7f89a5-2c1b-4ef0-bed6-e0f8299809c1"
  },
  {
    "listeners": 319,
    "recorded_at": "2025-11-16T03:44:41.125589+01:00",
    "raw_valid": true,
    "song_session_id": "8b7f89a5-2c1b-4ef0-bed6-e0f8299809c1"
  },
  {
    "listeners": 316,
    "recorded_at": "2025-11-16T03:45:11.128910+01:00",
    "raw_valid": true,
    "song_session_id": "8b7f89a5-2c1b-4ef0-bed6-e0f8299809c1"
  },
  {
    "listeners": 322,
    "recorded_at": "2025-11-16T03:45:41.129839+01:00",
    "raw_valid": true,
    "song_session_id": "8b7f89a5-2c1b-4ef0-bed6-e0f8299809c1"
  },
  {
    "listeners": 316,
    "recorded_at": "2025-11-16T03:46:11.133671+01:00",
    "raw_valid": true,
    "song_session_id": "8b7f89a5-2c1b-4ef0-bed6-e0f8299809c1"
  },
  {
    "listeners": 324,
    "recorded_at": "2025-11-16T03:46:41.135369+01:00",
    "raw_valid": true,
    "song_session_id": "8b7f89a5-2c1b-4ef0-bed6-e0f8299809c1"
  },
  {
    "listeners": 324,
    "recorded_at": "2025-11-16T03:47:11.136673+01:00",
    "raw_valid": true,
    "song_session_id": "8b7f89a5-2c1b-4ef0-bed6-e0f8299809c1"
  },
  {
    "listeners": 318,
    "recorded_at": "2025-11-16T03:47:41.163148+01:00",
    "raw_valid": true,
    "song_session_id": "8b7f89a5-2c1b-4ef0-bed6-e0f8299809c1"
  },
  {
    "listeners": 323,
    "recorded_at": "2025-11-16T03:48:11.193582+01:00",
    "raw_valid": true,
    "song_session_id": "b40bc46e-f1a9-4d28-ba0c-5f385794fd5b"
  },
  {
    "listeners": 322,
    "recorded_at": "2025-11-16T03:48:41.213711+01:00",
    "raw_valid": true,
    "song_session_id": "b40bc46e-f1a9-4d28-ba0c-5f385794fd5b"
  },
  {
    "listeners": 322,
    "recorded_at": "2025-11-16T03:49:11.244117+01:00",
    "raw_valid": true,
    "song_session_id": "b40bc46e-f1a9-4d28-ba0c-5f385794fd5b"
  },
  {
    "listeners": 325,
    "recorded_at": "2025-11-16T03:49:41.245664+01:00",
    "raw_valid": true,
    "song_session_id": "b40bc46e-f1a9-4d28-ba0c-5f385794fd5b"
  },
  {
    "listeners": 315,
    "recorded_at": "2025-11-16T03:50:11.280180+01:00",
    "raw_valid": true,
    "song_session_id": "b40bc46e-f1a9-4d28-ba0c-5f385794fd5b"
  },
  {
    "listeners": 317,
    "recorded_at": "2025-11-16T03:50:41.310614+01:00",
    "raw_valid": true,
    "song_session_id": "b40bc46e-f1a9-4d28-ba0c-5f385794fd5b"
  },
  {
    "listeners": 323,
    "recorded_at": "2025-11-16T03:51:11.317667+01:00",
    "raw_valid": true,
    "song_session_id": "b40bc46e-f1a9-4d28-ba0c-5f385794fd5b"
  },
  {
    "listeners": 317,
    "recorded_at": "2025-11-16T03:51:41.325701+01:00",
    "raw_valid": true,
    "song_session_id": "b40bc46e-f1a9-4d28-ba0c-5f385794fd5b"
  },
  {
    "listeners": 320,
    "recorded_at": "2025-11-16T03:52:11.356120+01:00",
    "raw_valid": true,
    "song_session_id": "b40bc46e-f1a9-4d28-ba0c-5f385794fd5b"
  },
  {
    "listeners": 324,
    "recorded_at": "2025-11-16T03:52:41.386536+01:00",
    "raw_valid": true,
    "song_session_id": "af8ee2d5-6228-4a1a-a257-f2aca0f811fa"
  },
  {
    "listeners": 324,
    "recorded_at": "2025-11-16T03:53:11.416953+01:00",
    "raw_valid": true,
    "song_session_id": "af8ee2d5-6228-4a1a-a257-f2aca0f811fa"
  },
  {
    "listeners": 322,
    "recorded_at": "2025-11-16T03:53:41.440841+01:00",
    "raw_valid": true,
    "song_session_id": "af8ee2d5-6228-4a1a-a257-f2aca0f811fa"
  },
  {
    "listeners": 324,
    "recorded_at": "2025-11-16T03:54:11.453717+01:00",
    "raw_valid": true,
    "song_session_id": "af8ee2d5-6228-4a1a-a257-f2aca0f811fa"
  },
  {
    "listeners": 317,
    "recorded_at": "2025-11-16T03:54:41.481709+01:00",
    "raw_valid": true,
    "song_session_id": "af8ee2d5-6228-4a1a-a257-f2aca0f811fa"
  },
  {
    "listeners": 325,
    "recorded_at": "2025-11-16T03:55:51.963732+01:00",
    "raw_valid": true,
    "song_session_id": "af8ee2d5-6228-4a1a-a257-f2aca0f811fa"
  },
  {
    "listeners": 317,
    "recorded_at": "2025-11-16T03:56:21.967296+01:00",
    "raw_valid": true,
    "song_session_id": "2bc968de-45a0-4ef4-a812-8439ed9db875"
  },
  {
    "listeners": 321,
    "recorded_at": "2025-11-16T03:56:51.997803+01:00",
    "raw_valid": true,
    "song_session_id": "2bc968de-45a0-4ef4-a812-8439ed9db875"
  },
  {
    "listeners": 319,
    "recorded_at": "2025-11-16T03:58:02.624674+01:00",
    "raw_valid": true,
    "song_session_id": "2bc968de-45a0-4ef4-a812-8439ed9db875"
  },
  {
    "listeners": 316,
    "recorded_at": "2025-11-16T03:58:32.626108+01:00",
    "raw_valid": true,
    "song_session_id": "2bc968de-45a0-4ef4-a812-8439ed9db875"
  },
  {
    "listeners": 320,
    "recorded_at": "2025-11-16T03:59:02.636296+01:00",
    "raw_valid": true,
    "song_session_id": "2bc968de-45a0-4ef4-a812-8439ed9db875"
  },
  {
    "listeners": 325,
    "recorded_at": "2025-11-16T03:59:32.638415+01:00",
    "raw_valid": true,
    "song_session_id": "5dac1d1c-bfb8-47f4-82da-ca92d320298b"
  },
  {
    "listeners": 319,
    "recorded_at": "2025-11-16T04:00:02.640491+01:00",
    "raw_valid": true,
    "song_session_id": "5dac1d1c-bfb8-47f4-82da-ca92d320298b"
  },
  {
    "listeners": 323,
    "recorded_at": "2025-11-16T04:00:32.641845+01:00",
    "raw_valid": true,
    "song_session_id": "5dac1d1c-bfb8-47f4-82da-ca92d320298b"
  },
  {
    "listeners": 324,
    "recorded_at": "2025-11-16T04:01:02.646305+01:00",
    "raw_valid": true,
    "song_session_id": "5dac1d1c-bfb8-47f4-82da-ca92d320298b"
  },
  {
    "listeners": 319,
    "recorded_at": "2025-11-16T04:01:32.648642+01:00",
    "raw_valid": true,
    "song_session_id": "5dac1d1c-bfb8-47f4-82da-ca92d320298b"
  },
  {
    "listeners": 319,
    "recorded_at": "2025-11-16T04:02:02.650826+01:00",
    "raw_valid": true,
    "song_session_id": "5dac1d1c-bfb8-47f4-82da-ca92d320298b"
  },
  {
    "listeners": 318,
    "recorded_at": "2025-11-16T04:02:32.653127+01:00",
    "raw_valid": true,
    "song_session_id": "173db9b0-61db-4ebe-a76b-488480f0f4bf"
  },
  {
    "listeners": 315,
    "recorded_at": "2025-11-16T04:03:02.654319+01:00",
    "raw_valid": true,
    "song_session_id": "173db9b0-61db-4ebe-a76b-488480f0f4bf"
  }
]