[
  {
    "song": "Skusky Z Lasky",
    "artists": [
      "Gravis"
    ],
    "isrc": "SKA128912006",
    "start_time": "2025-11-16 02:03:35",
    "radio": "expres",
    "recorded_at": "2025-11-16T02:04:08.888389+01:00",
    "raw_valid": true,
    "song_session_id": "cf151ded-2a16-4423-84e3-51abe0a93ac0",
    "duration_ms": 245179,
    "genre": []
  },
  {
    "song": "Ray Of Light",
    "artists": [
      "Nico Santos"
    ],
    "isrc": "DECE72402394",
    "start_time": "2025-11-16 02:07:16",
    "radio": "expres",
    "recorded_at": "2025-11-16T02:07:54.556228+01:00",
    "raw_valid": true,
    "song_session_id": "5c788c2d-67d1-49bb-bded-d1ba8fdfbf5b",
    "duration_ms": 176500,
    "genre": []
  },
  {
    "song": "Staci Si Priat",
    "artists": [
      "Zuzana Smatanova"
    ],
    "isrc": "CZA210900978",
    "start_time": "2025-11-16 02:10:14",
    "radio": "expres",
    "recorded_at": "2025-11-16T02:10:37.479197+01:00",
    "raw_valid": true,
    "song_session_id": "ee6912d6-5f93-46ee-9418-a9407c29b65f",
    "duration_ms": 215506,
    "genre": []
  },
  {
    "song": "Africa",
    "artists": [
      "Toto"
    ],
    "isrc": "USSM19801941",
    "start_time": "2025-11-16 02:13:54",
    "radio": "expres",
    "recorded_at": "2025-11-16T02:14:21.286375+01:00",
    "raw_valid": true,
    "song_session_id": "73d770aa-b9ef-4011-80c6-dac9a412f3a5",
    "duration_ms": 296200,
    "genre": [
      "rock"
    ]
  },
  {
    "song": "Vesmir",
    "artists": [
      "Lina Mayer"
    ],
    "isrc": "SKK312300202",
    "start_time": "2025-11-16 02:18:36",
    "radio": "expres",
    "recorded_at": "2025-11-16T02:19:16.394711+01:00",
    "raw_valid": true,
    "song_session_id": "8a3b94ff-8e6d-41b5-991b-b6ad19f02e09",
    "duration_ms": 235054,
    "genre": []
  },
  {
    "song": "Gone Gone Gone",
    "artists": [
      "David Guetta",
      "Teddy Swims",
      "Tones And I"
    ],
    "isrc": "UKWLG2500132",
    "start_time": "2025-11-16 02:22:24",
    "radio": "expres",
    "recorded_at": "2025-11-16T02:23:04.839343+01:00",
    "raw_valid": true,
    "song_session_id": "a85f8e3b-cfd4-43aa-86e4-4a7e30098e38",
    "duration_ms": 198004,
    "genre": [
      "soul"
    ]
  },
  {
    "song": "Neuc Vtaka Lietat",
    "artists": [
      "Richard Muller"
    ],
    "isrc": "CZA110111007",
    "start_time": "2025-11-16 02:26:05",
    "radio": "expres",
    "recorded_at": "2025-11-16T02:26:38.016382+01:00",
    "raw_valid": true,
    "song_session_id": "d9da278e-26a2-4aca-9c6e-c5bafd3d0bed",
    "duration_ms": 226146,
    "genre": []
  },
  {
    "song": "Gimme Love",
    "artists": [
      "Sia"
    ],
    "isrc": "USAT22307798",
    "start_time": "2025-11-16 02:29:47",
    "radio": "expres",
    "recorded_at": "2025-11-16T02:30:36.222530+01:00",
    "raw_valid": true,
    "song_session_id": "b6f682fb-3443-4ff7-bf5c-79503df0d029",
    "duration_ms": 214074,
    "genre": []
  },
  {
    "song": "Million Good Reasons",
    "artists": [
      "Robin Schulz",
      "Fast Boy"
    ],
    "isrc": "DEA622404738",
    "start_time": "2025-11-16 02:32:50",
    "radio": "expres",
    "recorded_at": "2025-11-16T02:33:30.002383+01:00",
    "raw_valid": true,
    "song_session_id": "108737c7-000a-46d8-bdec-e4ef8b685a99",
    "duration_ms": 157130,
    "genre": []
  },
  {
    "song": "Svety",
    "artists": [
      "Katarina Knechtova"
    ],
    "isrc": "SKE431800134",
    "start_time": "2025-11-16 02:35:26",
    "radio": "expres",
    "recorded_at": "2025-11-16T02:35:56.741495+01:00",
    "raw_valid": true,
    "song_session_id": "94354e56-da4d-4ce8-b83e-6b14caa289e1",
    "duration_ms": 231493,
    "genre": []
  },
  {
    "song": "Another Love",
    "artists": [
      "Tom Odell"
    ],
    "isrc": "GBARL1300107",
    "start_time": "2025-11-16 02:39:14",
    "radio": "expres",
    "recorded_at": "2025-11-16T02:39:40.302929+01:00",
    "raw_valid": true,
    "song_session_id": "589635be-46e8-4b4d-8439-92a546c5e79d",
    "duration_ms": 246040,
    "genre": [
      "rock"
    ]
  },
  {
    "song": "Osmy Svetadiel",
    "artists": [
      "Elan"
    ],
    "isrc": "TCAEF1942463",
    "start_time": "2025-11-16 02:43:26",
    "radio": "expres",
    "recorded_at": "2025-11-16T02:43:59.041599+01:00",
    "raw_valid": true,
    "song_session_id": "908e5b70-33f3-483e-868c-0ce65938694d",
    "duration_ms": 249000,
    "genre": []
  },
  {
    "song": "Golden",
    "artists": [
      "Kpop Demon Hunters"
    ],
    "isrc": "QZ8BZ2513510",
    "start_time": "2025-11-16 02:47:28",
    "radio": "expres",
    "recorded_at": "2025-11-16T02:47:59.812764+01:00",
    "raw_valid": true,
    "song_session_id": "2314c69c-660b-4ca0-99b0-c685bed77cce",
    "duration_ms": 194607,
    "genre": [
      "korean"
    ]
  },
  {
    "song": "Vrat Trochu Lasky Medzi Nas",
    "artists": [
      "Money Factor"
    ],
    "isrc": "FRX201742441",
    "start_time": "2025-11-16 02:50:10",
    "radio": "expres",
    "recorded_at": "2025-11-16T02:50:47.479549+01:00",
    "raw_valid": true,
    "song_session_id": "5df4ab14-ddc2-4a45-bd0a-3da7fda823ab",
    "duration_ms": 245640,
    "genre": []
  },
  {
    "song": "Whenever Wherever",
    "artists": [
      "Shakira"
    ],
    "isrc": "NLB630100324",
    "start_time": "2025-11-16 02:54:21",
    "radio": "expres",
    "recorded_at": "2025-11-16T02:55:05.776725+01:00",
    "raw_valid": true,
    "song_session_id": "1a147431-314f-4c96-b63d-9b36048c92e6",
    "duration_ms": 196013,
    "genre": [
      "rock"
    ]
  },
  {
    "song": "Ako Malo",
    "artists": [
      "Team"
    ],
    "isrc": "SKA010700070",
    "start_time": "2025-11-16 02:57:38",
    "radio": "expres",
    "recorded_at": "2025-11-16T02:58:25.001699+01:00",
    "raw_valid": true,
    "song_session_id": "cfc66d12-66df-4a0e-a095-e5d6639a7ff0",
    "duration_ms": 241426,
    "genre": []
  },
  {
    "song": "Italodisco",
    "artists": [
      "The Kolors"
    ],
    "isrc": "ITQ002300342",
    "start_time": "2025-11-16 03:01:34",
    "radio": "expres",
    "recorded_at": "2025-11-16T03:02:03.491780+01:00",
    "raw_valid": true,
    "song_session_id": "563dcde7-eaff-4cf3-bcbb-9ed0b02a909e",
    "duration_ms": 199512,
    "genre": [
      "pop"
    ]
  },
  {
    "song": "Kristinka Iba Spi",
    "artists": [
      "Peter Nagy"
    ],
    "isrc": "SKA128456906",
    "start_time": "2025-11-16 03:05:03",
    "radio": "expres",
    "recorded_at": "2025-11-16T03:05:27.929841+01:00",
    "raw_valid": true,
    "song_session_id": "eaed4cad-e02b-4106-b379-116aa6f1a7ff",
    "duration_ms": 293826,
    "genre": []
  },
  {
    "song": "Be Mine",
    "artists": [
      "Kamrad"
    ],
    "isrc": "DE1NJ2500035",
    "start_time": "2025-11-16 03:09:48",
    "radio": "expres",
    "recorded_at": "2025-11-16T03:10:12.350318+01:00",
    "raw_valid": true,
    "song_session_id": "e401cc74-c26b-456b-b31d-b35182772aad",
    "duration_ms": 156463,
    "genre": []
  },
  {
    "song": "Horehronie",
    "artists": [
      "Kristina"
    ],
    "isrc": "SKA011000098",
    "start_time": "2025-11-16 03:12:26",
    "radio": "expres",
    "recorded_at": "2025-11-16T03:13:04.617198+01:00",
    "raw_valid": true,
    "song_session_id": "c1425ae9-b036-4fd4-a724-c656b6b31e3e",
    "duration_ms": 183146,
    "genre": [
      "remark/catchy"
    ]
  },
  {
    "song": "Its My Life",
    "artists": [
      "Bon Jovi"
    ],
    "isrc": "USIR20000145",
    "start_time": "2025-11-16 03:15:29",
    "radio": "expres",
    "recorded_at": "2025-11-16T03:16:00.327486+01:00",
    "raw_valid": true,
    "song_session_id": "7474dc0c-a95c-48d4-b1c4-8f222436f2e6",
    "duration_ms": 224600,
    "genre": [
      "rock"
    ]
  },
  {
    "song": "Slovenska",
    "artists": [
      "Miro Zbirka"
    ],
    "isrc": "CZUM72000500",
    "start_time": "2025-11-16 03:19:26",
    "radio": "expres",
    "recorded_at": "2025-11-16T03:20:09.576733+01:00",
    "raw_valid": true,
    "song_session_id": "e6193958-c488-43e0-9f52-470a24d682eb",
    "duration_ms": 193373,
    "genre": []
  },
  {
    "song": "The Fate Of Ophelia",
    "artists": [
      "Taylor Swift"
    ],
    "isrc": "USUG12506436",
    "start_time": "2025-11-16 03:22:34",
    "radio": "expres",
    "recorded_at": "2025-11-16T03:23:07.418765+01:00",
    "raw_valid": true,
    "song_session_id": "330059d6-255c-4015-8efb-c3290d8ac278",
    "duration_ms": 226073,
    "genre": [
      "electronic"
    ]
  },
  {
    "song": "Vcely",
    "artists": [
      "Zuzana Smatanova"
    ],
    "isrc": "CZA210700536",
    "start_time": "2025-11-16 03:26:23",
    "radio": "expres",
    "recorded_at": "2025-11-16T03:27:04.923030+01:00",
    "raw_valid": true,
    "song_session_id": "4eddd1d1-a732-4bd6-9a18-906b4dfe5eab",
    "duration_ms": 185626,
    "genre": []
  },
  {
    "song": "Sorry Im Here For Someone Else",
    "artists": [
      "Benson Boone"
    ],
    "isrc": "USWB12500464",
    "start_time": "2025-11-16 03:29:36",
    "radio": "expres",
    "recorded_at": "2025-11-16T03:29:59.158256+01:00",
    "raw_valid": true,
    "song_session_id": "80c31bc4-72df-4adc-a48c-3565c4f45925",
    "duration_ms": 156582,
    "genre": []
  },
  {
    "song": "The One",
    "artists": [
      "Michael Patrick Kelly"
    ],
    "isrc": "DEE862500476",
    "start_time": "2025-11-16 03:32:48",
    "radio": "expres",
    "recorded_at": "2025-11-16T03:33:32.026483+01:00",
    "raw_valid": true,
    "song_session_id": "c1d7b1e9-d6cf-492b-a835-1c04f87dcbad",
    "duration_ms": 181194,
    "genre": []
  },
  {
    "song": "Run Run Run",
    "artists": [
      "Celeste Buckingham"
    ],
    "isrc": "QMQNX1200004",
    "start_time": "2025-11-16 03:35:44",
    "radio": "expres",
    "recorded_at": "2025-11-16T03:36:10.299928+01:00",
    "raw_valid": true,
    "song_session_id": "6fd9d0c1-4701-46b1-a7db-4d7f443ca101",
    "duration_ms": 224027,
    "genre": []
  },
  {
    "song": "Comin Home",
    "artists": [
      "Diddy-Dirty Money",
      "Skylar Grey"
    ],
    "isrc": "USUM71027542",
    "start_time": "2025-11-16 03:39:14",
    "radio": "expres",
    "recorded_at": "2025-11-16T03:39:38.373218+01:00",
    "raw_valid": true,
    "song_session_id": "b146b55d-9b64-4eec-9227-81012f7a79c5",
    "duration_ms": 238693,
    "genre": [
      "pop"
    ]
  },
  {
    "song": "Tvoj Mono Hlas",
    "artists": [
      "Nocaden"
    ],
    "isrc": "SKA010600009",
    "start_time": "2025-11-16 03:43:25",
    "radio": "expres",
    "recorded_at": "2025-11-16T03:43:58.360815+01:00",
    "raw_valid": true,
    "song_session_id": "b5f5abf8-a281-4a89-af69-5934480fb895",
    "duration_ms": 230093,
    "genre": []
  },
  {
    "song": "It Must Have Been Love",
    "artists": [
      "Roxette"
    ],
    "isrc": "SEAMA8777131",
    "start_time": "2025-11-16 03:47:19",
    "radio": "expres",
    "recorded_at": "2025-11-16T03:48:00.238810+01:00",
    "raw_valid": true,
    "song_session_id": "0fd2bcec-7b04-49d3-8278-ee7fabbf9ece",
    "duration_ms": 259666,
    "genre": [
      "rock"
    ]
  },
  {
    "song": "Vsetko Bude Dobre",
    "artists": [
      "Gladiator"
    ],
    "isrc": "SKCM72560001",
    "start_time": "2025-11-16 03:50:25",
    "radio": "expres",
    "recorded_at": "2025-11-16T03:51:04.070968+01:00",
    "raw_valid": true,
    "song_session_id": "d210e9d8-82e2-47ac-bc5d-ae6cf29fbbdc",
    "duration_ms": 166588,
    "genre": []
  },
  {
    "song": "End Of The World",
    "artists": [
      "Miley Cyrus"
    ],
    "isrc": "USSM12501019",
    "start_time": "2025-11-16 03:53:25",
    "radio": "expres",
    "recorded_at": "2025-11-16T03:53:46.640202+01:00",
    "raw_valid": true,
    "song_session_id": "b21ea11e-cca2-4a7d-a597-8b92bc78778a",
    "duration_ms": 250483,
    "genre": [
      "rock"
    ]
  },
  {
    "song": "Slnecna Balada",
    "artists": [
      "Peha"
    ],
    "isrc": "SKA770305110",
    "start_time": "2025-11-16 03:57:32",
    "radio": "expres",
    "recorded_at": "2025-11-16T03:58:05.159021+01:00",
    "raw_valid": true,
    "song_session_id": "be692330-7faf-485b-9e8b-47fa69d9e044",
    "duration_ms": 233266,
    "genre": []
  },
  {
    "song": "Glide",
    "artists": [
      "Neiked",
      "Portugal The Man"
    ],
    "isrc": "DEE862500421",
    "start_time": "2025-11-16 04:01:17",
    "radio": "expres",
    "recorded_at": "2025-11-16T04:01:43.631606+01:00",
    "raw_valid": true,
    "song_session_id": "da9ed3d6-e4b7-44de-a912-9113e70ee07b",
    "duration_ms": 184405,
    "genre": []
  }
]