[
  {
    "last_update": "2025-12-11 18:03:12",
    "song": {
      "musicAuthor": "Post Malone",
      "musicCover": "https://i.scdn.co/image/ab67616d0000485197306976e3eb8aad53b754eb",
      "musicTitle": "I Had Some Help",
      "radio": "Fun Rádio",
      "startTime": "19:02"
    },
    "recorded_at": "2025-12-11T19:03:13.747590+01:00",
    "raw_valid": true,
    "song_session_id": "bceb871b-e087-4c6c-b21e-144b9c977f34",
    "duration_ms": 178205,
    "genre": []
  },
  {
    "last_update": "2025-12-11 18:06:13",
    "song": {
      "musicAuthor": "Huntrix Featuring Ejae & Audrey Nuna",
      "musicCover": "https://i.scdn.co/image/ab6742d3000052b717f3963ae4a9f5422763140e",
      "musicTitle": "Golden",
      "radio": "Fun Rádio",
      "startTime": "19:05"
    },
    "recorded_at": "2025-12-11T19:06:13.914391+01:00",
    "raw_valid": true,
    "song_session_id": "6a2e49cf-a6d6-4d08-bd02-0b08b276bfc7",
    "duration_ms": 194608,
    "genre": []
  },
  {
    "last_update": "2025-12-11 18:09:13",
    "song": {
      "musicAuthor": "David Guetta, Teddy Swims, Tones And I",
      "musicCover": "https://i.scdn.co/image/ab67616d00004851dff5897733ec36cdb24db9a2",
      "musicTitle": "Gone Gone Gone",
      "radio": "Fun Rádio",
      "startTime": "19:08"
    },
    "recorded_at": "2025-12-11T19:09:14.206653+01:00",
    "raw_valid": true,
    "song_session_id": "a23be06c-1484-4dbb-b2d9-333a120190b7",
    "duration_ms": 198004,
    "genre": []
  },
  {
    "last_update": "2025-12-11 18:15:13",
    "song": {
      "musicAuthor": "Olly Murs",
      "musicCover": "https://i.scdn.co/image/ab67616d00004851f8d31ce65b9b9d08e03b4328",
      "musicTitle": "Bonkers",
      "radio": "Fun Rádio",
      "startTime": "19:14"
    },
    "recorded_at": "2025-12-11T19:15:14.643116+01:00",
    "raw_valid": true,
    "song_session_id": "17be8595-a0e8-4cca-b818-5dabcd4032f2",
    "duration_ms": 143452,
    "genre": []
  },
  {
    "last_update": "2025-12-11 18:17:13",
    "song": {
      "musicAuthor": "Martin Garrix & Lauv",
      "musicCover": "https://i.scdn.co/image/ab67616d000048515c0e5abe73559c2de9d2eee0",
      "musicTitle": "Mad",
      "radio": "Fun Rádio",
      "startTime": "19:16"
    },
    "recorded_at": "2025-12-11T19:17:14.761797+01:00",
    "raw_valid": true,
    "song_session_id": "04efd288-698b-4149-85a4-3b990f7908b3",
    "duration_ms": 199804,
    "genre": []
  },
  {
    "last_update": "2025-12-11 18:21:14",
    "song": {
      "musicAuthor": "Alex Warren",
      "musicCover": "https://i.scdn.co/image/ab67616d00004851b0a2d7a2d8406a4a72a92d5c",
      "musicTitle": "Eternity",
      "radio": "Fun Rádio",
      "startTime": "19:20"
    },
    "recorded_at": "2025-12-11T19:21:15.004431+01:00",
    "raw_valid": true,
    "song_session_id": "b658907d-ac25-4b47-a327-41a09c108aea",
    "duration_ms": 189553,
    "genre": []
  },
  {
    "last_update": "2025-12-11 18:24:14",
    "song": {
      "musicAuthor": "James Hype Feat Sam Harper & Bobby Harvey",
      "musicCover": "https://i.scdn.co/image/ab67616d00004851f60d7f051679fab1ecb2a381",
      "musicTitle": "Waterfalls",
      "radio": "Fun Rádio",
      "startTime": "19:23"
    },
    "recorded_at": "2025-12-11T19:24:15.257204+01:00",
    "raw_valid": true,
    "song_session_id": "059b483d-1e10-435c-86f8-f601223a0eea",
    "duration_ms": 120578,
    "genre": []
  },
  {
    "last_update": "2025-12-11 18:31:15",
    "song": {
      "musicAuthor": "Shaboozey",
      "musicCover": "https://i.scdn.co/image/ab67616d0000485180d86d636244b72a3a1eede2",
      "musicTitle": "A Bar Song (Tipsy)",
      "radio": "Fun Rádio",
      "startTime": "19:30"
    },
    "recorded_at": "2025-12-11T19:31:15.692514+01:00",
    "raw_valid": true,
    "song_session_id": "c6e2a3ee-817c-4eb6-875e-0441bdcc028c",
    "duration_ms": 171291,
    "genre": [
      "country"
    ]
  },
  {
    "last_update": "2025-12-11 18:34:16",
    "song": {
      "musicAuthor": "Michael Schulte & Asdis",
      "musicCover": "https://i.scdn.co/image/ab67616d000048518710df06af6a51d6c9e3439f",
      "musicTitle": "Half Of My Heart",
      "radio": "Fun Rádio",
      "startTime": "19:33"
    },
    "recorded_at": "2025-12-11T19:34:16.023072+01:00",
    "raw_valid": true,
    "song_session_id": "d52f9082-f725-4044-b43d-1c7d4bf176cb",
    "duration_ms": 158320,
    "genre": []
  },
  {
    "last_update": "2025-12-11 18:37:15",
    "song": {
      "musicAuthor": "Iamchino & Pitbull & Flo Rida",
      "musicCover": "https://i.scdn.co/image/ab67616d00004851fa853d9769c89d08a74983bb",
      "musicTitle": "Borracho Y Loco",
      "radio": "Fun Rádio",
      "startTime": "19:36"
    },
    "recorded_at": "2025-12-11T19:37:16.428675+01:00",
    "raw_valid": true,
    "song_session_id": "32e8170f-12b1-40e2-9284-9329531e0331",
    "duration_ms": 164542,
    "genre": []
  },
  {
    "last_update": "2025-12-11 18:42:16",
    "song": {
      "musicAuthor": "Sombr",
      "musicCover": "https://i.scdn.co/image/ab67616d00004851dad39d4906f76b7c176effb1",
      "musicTitle": "Undressed",
      "radio": "Fun Rádio",
      "startTime": "19:41"
    },
    "recorded_at": "2025-12-11T19:42:16.777729+01:00",
    "raw_valid": true,
    "song_session_id": "74c97eb6-ea61-4fff-8131-92bc5aa7744f",
    "duration_ms": 182088,
    "genre": [
      "rock"
    ]
  },
  {
    "last_update": "2025-12-11 18:45:16",
    "song": {
      "musicAuthor": "Ray Dalton",
      "musicCover": "https://i.scdn.co/image/ab67616d000048516877c9f39748f63d5fa5b964",
      "musicTitle": "Blood Running",
      "radio": "Fun Rádio",
      "startTime": "19:44"
    },
    "recorded_at": "2025-12-11T19:45:16.977858+01:00",
    "raw_valid": true,
    "song_session_id": "0f22731e-6946-4643-99b0-41604f48cb14",
    "duration_ms": 173146,
    "genre": []
  },
  {
    "last_update": "2025-12-11 18:48:17",
    "song": {
      "musicAuthor": "Celeste Buckingham",
      "musicCover": "https://static.radia.sk/covers/32/2678e8e1-7426-44ad-a98f-0b586115cd1c.jpg",
      "musicTitle": "Let It Snow",
      "radio": "Fun Rádio",
      "startTime": "19:47"
    },
    "recorded_at": "2025-12-11T19:48:17.279759+01:00",
    "raw_valid": true,
    "song_session_id": "4cf28032-9c60-46f0-bc12-fafa4c936ed1",
    "duration_ms": null,
    "genre": []
  },
  {
    "last_update": "2025-12-11 18:51:16",
    "song": {
      "musicAuthor": "Twocolors",
      "musicCover": "https://i.scdn.co/image/ab67616d0000485169a297296cd7e38dfb1c2ba5",
      "musicTitle": "Chemical",
      "radio": "Fun Rádio",
      "startTime": "19:50"
    },
    "recorded_at": "2025-12-11T19:51:17.648772+01:00",
    "raw_valid": true,
    "song_session_id": "cb9c0dea-a38d-466a-aed3-5a69ab7e09e0",
    "duration_ms": 166821,
    "genre": []
  },
  {
    "last_update": "2025-12-11 18:55:17",
    "song": {
      "musicAuthor": "Disco Lines & Tinashe",
      "musicCover": "https://i.scdn.co/image/ab67616d0000485169aa159daad3e671c749f4c5",
      "musicTitle": "No Broke Boys",
      "radio": "Fun Rádio",
      "startTime": "19:54"
    },
    "recorded_at": "2025-12-11T19:55:17.896511+01:00",
    "raw_valid": true,
    "song_session_id": "7acca456-c8ba-4d85-920d-00104e22f5b7",
    "duration_ms": 163994,
    "genre": []
  },
  {
    "last_update": "2025-12-11 19:01:18",
    "song": {
      "musicAuthor": "Dara Rolins & Tomi Popovič",
      "musicCover": "https://i.scdn.co/image/ab67616d000048512efe97171504b3a6bd14e69f",
      "musicTitle": "Nebo, Peklo, Raj",
      "radio": "Fun Rádio",
      "startTime": "20:00"
    },
    "recorded_at": "2025-12-11T20:01:18.366936+01:00",
    "raw_valid": true,
    "song_session_id": "c7932774-16bd-4292-9928-6c6ac1875255",
    "duration_ms": 214440,
    "genre": []
  },
  {
    "last_update": "2025-12-11 19:04:17",
    "song": {
      "musicAuthor": "Katarína Knechtová",
      "musicCover": "https://i.scdn.co/image/ab67616d00004851143d1dc0b4195aa6ded70e46",
      "musicTitle": "Verím",
      "radio": "Fun Rádio",
      "startTime": "20:03"
    },
    "recorded_at": "2025-12-11T20:04:18.578121+01:00",
    "raw_valid": true,
    "song_session_id": "1e81727e-b5da-463c-9328-6817249114c7",
    "duration_ms": 228830,
    "genre": []
  },
  {
    "last_update": "2025-12-11 19:07:18",
    "song": {
      "musicAuthor": "Amo Featuring Juraj Benetin",
      "musicCover": "https://i.scdn.co/image/ab67616d00004851bed3540e192334d7fc5e0d66",
      "musicTitle": "Femme Fatale",
      "radio": "Fun Rádio",
      "startTime": "20:07"
    },
    "recorded_at": "2025-12-11T20:07:18.815211+01:00",
    "raw_valid": true,
    "song_session_id": "69750e82-4075-4b8c-b3c1-578f9218cbdb",
    "duration_ms": 230200,
    "genre": []
  },
  {
    "last_update": "2025-12-11 19:11:18",
    "song": {
      "musicAuthor": "Kali, I.M.T. Smile",
      "musicCover": "https://i.scdn.co/image/ab67616d00004851ecbf49b6574cbe4126aee32c",
      "musicTitle": "Nič sa nemení",
      "radio": "Fun Rádio",
      "startTime": "20:10"
    },
    "recorded_at": "2025-12-11T20:11:19.094041+01:00",
    "raw_valid": true,
    "song_session_id": "1472c4d4-af97-4484-a69b-63462e14903f",
    "duration_ms": 206570,
    "genre": []
  },
  {
    "last_update": "2025-12-11 19:14:18",
    "song": {
      "musicAuthor": "Celeste Buckingham",
      "musicCover": "https://i.scdn.co/image/ab67616d000048514c8465bc8d5cf6a77629fc0d",
      "musicTitle": "Drive",
      "radio": "Fun Rádio",
      "startTime": "20:14"
    },
    "recorded_at": "2025-12-11T20:14:19.310011+01:00",
    "raw_valid": true,
    "song_session_id": "5e476f4f-2ac9-4143-82d6-33497a9d8f58",
    "duration_ms": 242281,
    "genre": []
  },
  {
    "last_update": "2025-12-11 19:19:19",
    "song": {
      "musicAuthor": "Peter Bič Project",
      "musicCover": "https://i.scdn.co/image/ab67616d00004851e7e20269d35bbfac097ad7de",
      "musicTitle": "Čoskoro",
      "radio": "Fun Rádio",
      "startTime": "20:18"
    },
    "recorded_at": "2025-12-11T20:19:19.617210+01:00",
    "raw_valid": true,
    "song_session_id": "8eff68f3-384c-4e8b-99fe-fd41d81a992f",
    "duration_ms": 207515,
    "genre": []
  },
  {
    "last_update": "2025-12-11 19:27:20",
    "song": {
      "musicAuthor": "Tublatanka",
      "musicCover": "https://i.scdn.co/image/ab67616d0000485153dbdfa6b6be3cdf8e1ddf20",
      "musicTitle": "Poďme Bratia Do Betlehema",
      "radio": "Fun Rádio",
      "startTime": "20:24"
    },
    "recorded_at": "2025-12-11T20:27:20.271954+01:00",
    "raw_valid": true,
    "song_session_id": "f5dfa18b-ba7c-4ff8-9aa1-9befab9b32b5",
    "duration_ms": 252706,
    "genre": []
  },
  {
    "last_update": "2025-12-11 19:30:19",
    "song": {
      "musicAuthor": "Emma Drobna",
      "musicCover": "https://i.scdn.co/image/ab67616d000048511d0977a2c8415382535ff224",
      "musicTitle": "Vo Vlnach",
      "radio": "Fun Rádio",
      "startTime": "20:29"
    },
    "recorded_at": "2025-12-11T20:30:20.591784+01:00",
    "raw_valid": true,
    "song_session_id": "29f0c36e-f009-4d95-9de5-4f192cad6a79",
    "duration_ms": 186891,
    "genre": []
  },
  {
    "last_update": "2025-12-11 19:33:20",
    "song": {
      "musicAuthor": "Lina Mayer",
      "musicCover": "https://i.scdn.co/image/ab67616d0000485139d2c18e23f40dc8fe4e1cd5",
      "musicTitle": "Stratená",
      "radio": "Fun Rádio",
      "startTime": "20:32"
    },
    "recorded_at": "2025-12-11T20:33:20.777632+01:00",
    "raw_valid": true,
    "song_session_id": "0306604d-10cf-4a28-b790-d05702f0630a",
    "duration_ms": 221304,
    "genre": []
  },
  {
    "last_update": "2025-12-11 19:37:20",
    "song": {
      "musicAuthor": "Matej Smutný",
      "musicCover": "https://i.scdn.co/image/ab67616d00004851fdcaee8193a5844c84fa8985",
      "musicTitle": "Psycho Love",
      "radio": "Fun Rádio",
      "startTime": "20:36"
    },
    "recorded_at": "2025-12-11T20:37:21.042130+01:00",
    "raw_valid": true,
    "song_session_id": "8608804b-fdeb-4c72-80f8-2469633f2d0e",
    "duration_ms": 220000,
    "genre": []
  },
  {
    "last_update": "2025-12-11 19:41:20",
    "song": {
      "musicAuthor": "Zuzana Smatanová",
      "musicCover": "https://i.scdn.co/image/ab67616d00004851fefe1a1ecc5375ca2590c771",
      "musicTitle": "Bergen",
      "radio": "Fun Rádio",
      "startTime": "20:40"
    },
    "recorded_at": "2025-12-11T20:41:21.306425+01:00",
    "raw_valid": true,
    "song_session_id": "c88629f7-62eb-40dc-9b45-dba8532a9824",
    "duration_ms": 235289,
    "genre": []
  },
  {
    "last_update": "2025-12-11 19:44:20",
    "song": {
      "musicAuthor": "Hex",
      "musicCover": "https://i.scdn.co/image/ab67616d000048510f84b352c86a11603fb21691",
      "musicTitle": "Ty A Ja",
      "radio": "Fun Rádio",
      "startTime": "20:43"
    },
    "recorded_at": "2025-12-11T20:44:21.501683+01:00",
    "raw_valid": true,
    "song_session_id": "4cb2b993-081c-4f74-8bf3-5ce2a0705774",
    "duration_ms": 240160,
    "genre": []
  },
  {
    "last_update": "2025-12-11 19:48:21",
    "song": {
      "musicAuthor": "Adam Ďurica",
      "musicCover": "https://i.scdn.co/image/ab67616d00004851af2ea0198ad8fc1ee245eb74",
      "musicTitle": "Drobnosti",
      "radio": "Fun Rádio",
      "startTime": "20:47"
    },
    "recorded_at": "2025-12-11T20:48:21.766054+01:00",
    "raw_valid": true,
    "song_session_id": "4342f619-1dd6-421b-98cc-6ab7ab51734f",
    "duration_ms": 230666,
    "genre": []
  },
  {
    "last_update": "2025-12-11 19:52:21",
    "song": {
      "musicAuthor": "Dominik Gerda",
      "musicCover": "https://i.scdn.co/image/ab67616d000048510b60101d54e2ce7dc8d6f9d6",
      "musicTitle": "Magical",
      "radio": "Fun Rádio",
      "startTime": "20:51"
    },
    "recorded_at": "2025-12-11T20:52:22.009160+01:00",
    "raw_valid": true,
    "song_session_id": "9933e18d-4114-4a71-98e0-98287e342453",
    "duration_ms": 219228,
    "genre": []
  }
]